{
  "meta": {
    "sources": {
      "varianti.lv": {
        "status": "ok",
        "count": 0
      },
      "ss.lv": {
        "status": "ok",
        "count": 160
      }
    },
    "started_at": "2026-06-30T10:01:28Z",
    "mode": "live",
    "finished_at": "2026-06-30T10:02:21Z",
    "total_listings": 122
  },
  "listings": [
    {
      "id": "ss-lv-ailhx",
      "source_id": "ailhx",
      "source_domain": "ss.lv",
      "source_url": "https://www.ss.lv/msg/lv/real-estate/flats/riga/centre/ailhx.html",
      "type": "apartment",
      "title": "Pieejams no 19.jūlija Īrei tiek piedāvāts dzīvoklis renovētā mā",
      "district": "Centrs",
      "street": "Artilērijas 26",
      "price": 560.0,
      "price_unit": "per_month",
      "currency": "EUR",
      "rooms": 2,
      "area": 38.0,
      "floor": "2/2",
      "year": null,
      "image": "https://i.ss.lv/gallery/8/1515/378707/75741261.jpg",
      "description": "",
      "amenities": [],
      "sub_type": null,
      "first_seen": "2026-06-30T10:01:53Z",
      "last_seen": "2026-06-30T10:01:53Z",
      "dedup_hash": "5a3b3412cf826296"
    },
    {
      "id": "ss-lv-ahjbx",
      "source_id": "ahjbx",
      "source_domain": "ss.lv",
      "source_url": "https://www.ss.lv/msg/lv/real-estate/flats/riga/centre/ahjbx.html",
      "type": "apartment",
      "title": "Tiek izīrēts studio tipa dzīvoklis ar visām ērtībām, piemērots 1",
      "district": "Centrs",
      "street": "Valdemāra 127",
      "price": 250.0,
      "price_unit": "per_month",
      "currency": "EUR",
      "rooms": 1,
      "area": 22.0,
      "floor": "6/6",
      "year": null,
      "image": "https://i.ss.lv/gallery/8/1490/372356/74471037.jpg",
      "description": "",
      "amenities": [],
      "sub_type": null,
      "first_seen": "2026-06-30T10:01:53Z",
      "last_seen": "2026-06-30T10:01:53Z",
      "dedup_hash": "92ac9da3ce243088"
    },
    {
      "id": "ss-lv-dbhml",
      "source_id": "dbhml",
      "source_domain": "ss.lv",
      "source_url": "https://www.ss.lv/msg/lv/real-estate/flats/riga/purvciems/dbhml.html",
      "type": "apartment",
      "title": "Mūsdienīgs dzīvoklis ar aktuālo remontu un mājīgu atmosfēru.",
      "district": "Purvciems",
      "street": "Purvciema 48",
      "price": 430.0,
      "price_unit": "per_month",
      "currency": "EUR",
      "rooms": 1,
      "area": 40.0,
      "floor": "5/5",
      "year": null,
      "image": "https://i.ss.lv/gallery/8/1417/354105/70820817.jpg",
      "description": "",
      "amenities": [],
      "sub_type": null,
      "first_seen": "2026-06-30T10:01:53Z",
      "last_seen": "2026-06-30T10:01:53Z",
      "dedup_hash": "03db9126424b4ad9"
    },
    {
      "id": "ss-lv-cdhfix",
      "source_id": "cdhfix",
      "source_domain": "ss.lv",
      "source_url": "https://www.ss.lv/msg/lv/real-estate/flats/riga/ziepniekkalns/cdhfix.html",
      "type": "apartment",
      "title": "Dzīvoklis ar pilnībā aprīkotu virtuvi un trauku mazgājamo mašīnu",
      "district": "Ziepniekkalns",
      "street": "Graudu 8",
      "price": 850.0,
      "price_unit": "per_month",
      "currency": "EUR",
      "rooms": 4,
      "area": 78.0,
      "floor": "1/5",
      "year": null,
      "image": "https://i.ss.lv/gallery/8/1515/378706/75741056.jpg",
      "description": "",
      "amenities": [],
      "sub_type": null,
      "first_seen": "2026-06-30T10:01:53Z",
      "last_seen": "2026-06-30T10:01:53Z",
      "dedup_hash": "9c193b19b7b7c96c"
    },
    {
      "id": "ss-lv-hedlp",
      "source_id": "hedlp",
      "source_domain": "ss.lv",
      "source_url": "https://www.ss.lv/msg/lv/real-estate/flats/riga/centre/hedlp.html",
      "type": "apartment",
      "title": "Fasādes māja, renovēta māja, slēgts pagalms, ieeja no ielas un p",
      "district": "Centrs",
      "street": "Čaka 44",
      "price": 950.0,
      "price_unit": "per_month",
      "currency": "EUR",
      "rooms": 4,
      "area": 100.0,
      "floor": "2/5",
      "year": null,
      "image": "https://i.ss.lv/gallery/8/1514/378265/75652822.jpg",
      "description": "",
      "amenities": [],
      "sub_type": null,
      "first_seen": "2026-06-30T10:01:53Z",
      "last_seen": "2026-06-30T10:01:53Z",
      "dedup_hash": "3daf74701f07c67a"
    },
    {
      "id": "ss-lv-abegm",
      "source_id": "abegm",
      "source_domain": "ss.lv",
      "source_url": "https://www.ss.lv/msg/lv/real-estate/flats/riga/centre/abegm.html",
      "type": "apartment",
      "title": "Īrei tiek piedāvāts 2 istabu dzīvoklis Rīgas centrā. Dzīvoklis",
      "district": "Centrs",
      "street": "Marijas 16",
      "price": 550.0,
      "price_unit": "per_month",
      "currency": "EUR",
      "rooms": 2,
      "area": 46.0,
      "floor": "6/7",
      "year": null,
      "image": "https://i.ss.lv/gallery/8/1515/378703/75740551.jpg",
      "description": "",
      "amenities": [],
      "sub_type": null,
      "first_seen": "2026-06-30T10:01:53Z",
      "last_seen": "2026-06-30T10:01:53Z",
      "dedup_hash": "572f4d5fe62cfb68"
    },
    {
      "id": "ss-lv-aheof",
      "source_id": "aheof",
      "source_domain": "ss.lv",
      "source_url": "https://www.ss.lv/msg/lv/real-estate/flats/riga/agenskalns/aheof.html",
      "type": "apartment",
      "title": "Izīrē šarmantu 3 istabu dzīvokli Āgenskalnā – zaļajā, pieprasīta",
      "district": "Āgenskalns",
      "street": "Daugavgrīvas 3",
      "price": 750.0,
      "price_unit": "per_month",
      "currency": "EUR",
      "rooms": 3,
      "area": 59.0,
      "floor": "1/4",
      "year": null,
      "image": "https://i.ss.lv/gallery/8/1515/378703/75740474.jpg",
      "description": "",
      "amenities": [],
      "sub_type": null,
      "first_seen": "2026-06-30T10:01:53Z",
      "last_seen": "2026-06-30T10:01:53Z",
      "dedup_hash": "931b628a59fe9965"
    },
    {
      "id": "ss-lv-egemb",
      "source_id": "egemb",
      "source_domain": "ss.lv",
      "source_url": "https://www.ss.lv/msg/lv/real-estate/flats/riga/centre/egemb.html",
      "type": "apartment",
      "title": "Izīrē gaišu, mājīgu un plašu divistabu dzīvokli pēc kosmētiskā r",
      "district": "Centrs",
      "street": "Grostonas 25",
      "price": 890.0,
      "price_unit": "per_month",
      "currency": "EUR",
      "rooms": 2,
      "area": 65.0,
      "floor": "8/23",
      "year": null,
      "image": "https://i.ss.lv/gallery/8/1509/377131/75426075.jpg",
      "description": "",
      "amenities": [],
      "sub_type": null,
      "first_seen": "2026-06-30T10:01:53Z",
      "last_seen": "2026-06-30T10:01:53Z",
      "dedup_hash": "e144668b7845999f"
    },
    {
      "id": "ss-lv-ahpne",
      "source_id": "ahpne",
      "source_domain": "ss.lv",
      "source_url": "https://www.ss.lv/msg/lv/real-estate/flats/riga/centre/ahpne.html",
      "type": "apartment",
      "title": "Tiek piedāvāts 2-ist. -dzīvoklis ar visam ērtībām. Augstais 1.st",
      "district": "Centrs",
      "street": "Lastādijas 39A",
      "price": 395.0,
      "price_unit": "per_month",
      "currency": "EUR",
      "rooms": 2,
      "area": 52.0,
      "floor": "1/6",
      "year": null,
      "image": "https://i.ss.lv/gallery/8/1515/378674/75734675.jpg",
      "description": "",
      "amenities": [],
      "sub_type": null,
      "first_seen": "2026-06-30T10:01:53Z",
      "last_seen": "2026-06-30T10:01:53Z",
      "dedup_hash": "22e0f44d07b8d2f8"
    },
    {
      "id": "ss-lv-cdjdxk",
      "source_id": "cdjdxk",
      "source_domain": "ss.lv",
      "source_url": "https://www.ss.lv/msg/lv/real-estate/flats/riga/chiekurkalns/cdjdxk.html",
      "type": "apartment",
      "title": "Izīrē vienistabas dzīvokli Čiekurkalnā, 32 m². Dzīvoklis ir ar k",
      "district": "Čiekurkalns",
      "street": "Čiekurkalna 1. l. 7",
      "price": 250.0,
      "price_unit": "per_month",
      "currency": "EUR",
      "rooms": 1,
      "area": 32.0,
      "floor": "2/2",
      "year": null,
      "image": "https://i.ss.lv/gallery/8/1455/363540/72707992.jpg",
      "description": "",
      "amenities": [],
      "sub_type": null,
      "first_seen": "2026-06-30T10:01:53Z",
      "last_seen": "2026-06-30T10:01:53Z",
      "dedup_hash": "64ce2438fbf2d37f"
    },
    {
      "id": "ss-lv-idoie",
      "source_id": "idoie",
      "source_domain": "ss.lv",
      "source_url": "https://www.ss.lv/msg/lv/real-estate/flats/riga/purvciems/idoie.html",
      "type": "apartment",
      "title": "Сдаётся большая однокомнатная квартира. Платежеспособной семье,",
      "district": "Purvciems",
      "street": "Madonas 23",
      "price": 280.0,
      "price_unit": "per_month",
      "currency": "EUR",
      "rooms": 1,
      "area": 53.0,
      "floor": "6/16",
      "year": null,
      "image": "https://i.ss.lv/gallery/8/1453/363182/72636375.jpg",
      "description": "",
      "amenities": [],
      "sub_type": null,
      "first_seen": "2026-06-30T10:01:53Z",
      "last_seen": "2026-06-30T10:01:53Z",
      "dedup_hash": "8af33776a32cc6c1"
    },
    {
      "id": "ss-lv-adkog",
      "source_id": "adkog",
      "source_domain": "ss.lv",
      "source_url": "https://www.ss.lv/msg/lv/real-estate/flats/riga/centre/adkog.html",
      "type": "apartment",
      "title": "Ilgtermiņā izīrē 2 izolētu istabu dzīvokli pēc kapitālā kvalitat",
      "district": "Centrs",
      "street": "Tērbatas 59/61",
      "price": 780.0,
      "price_unit": "per_month",
      "currency": "EUR",
      "rooms": 2,
      "area": 60.0,
      "floor": "5/5",
      "year": null,
      "image": "https://i.ss.lv/gallery/7/1231/307616/61523008.jpg",
      "description": "",
      "amenities": [],
      "sub_type": null,
      "first_seen": "2026-06-30T10:01:53Z",
      "last_seen": "2026-06-30T10:01:53Z",
      "dedup_hash": "f1538a095bddc0fc"
    },
    {
      "id": "ss-lv-bmopgo",
      "source_id": "bmopgo",
      "source_domain": "ss.lv",
      "source_url": "https://www.ss.lv/msg/lv/real-estate/flats/riga/shampeteris-pleskodale/bmopgo.html",
      "type": "apartment",
      "title": "Izīrē mājīgu divistabu dzīvokli Rīgā – Volguntes ielā 21, Šampēt",
      "district": "Unknown",
      "street": "Šampēteris-Pleskodāle Volguntes 21",
      "price": 330.0,
      "price_unit": "per_month",
      "currency": "EUR",
      "rooms": 2,
      "area": 38.0,
      "floor": "2/5",
      "year": null,
      "image": "https://i.ss.lv/gallery/8/1465/366126/73225098.jpg",
      "description": "",
      "amenities": [],
      "sub_type": null,
      "first_seen": "2026-06-30T10:01:53Z",
      "last_seen": "2026-06-30T10:01:53Z",
      "dedup_hash": "42ae2e83b5f0f81f"
    },
    {
      "id": "ss-lv-akkdn",
      "source_id": "akkdn",
      "source_domain": "ss.lv",
      "source_url": "https://www.ss.lv/msg/lv/real-estate/flats/riga/mezhciems/akkdn.html",
      "type": "apartment",
      "title": "No 1. jūlija tiek izīrēts gaišs un mājīgs 2 istabu dzīvoklis Mež",
      "district": "Unknown",
      "street": "Mežciems Kaivas 50k1",
      "price": 570.0,
      "price_unit": "per_month",
      "currency": "EUR",
      "rooms": 2,
      "area": 51.0,
      "floor": "3/5",
      "year": null,
      "image": "https://i.ss.lv/gallery/8/1514/378309/75661649.jpg",
      "description": "",
      "amenities": [],
      "sub_type": null,
      "first_seen": "2026-06-30T10:01:53Z",
      "last_seen": "2026-06-30T10:01:53Z",
      "dedup_hash": "b4e3a336380321b8"
    },
    {
      "id": "ss-lv-ehipm",
      "source_id": "ehipm",
      "source_domain": "ss.lv",
      "source_url": "https://www.ss.lv/msg/lv/real-estate/flats/riga/centre/ehipm.html",
      "type": "apartment",
      "title": "Izmanto iespēju dzīvot Hospitāļu ielā kvalitatīvi izremontētā st",
      "district": "Centrs",
      "street": "Hospitāļu 3",
      "price": 380.0,
      "price_unit": "per_month",
      "currency": "EUR",
      "rooms": 1,
      "area": 25.0,
      "floor": "3/6",
      "year": null,
      "image": "https://i.ss.lv/gallery/8/1515/378697/75739257.jpg",
      "description": "",
      "amenities": [],
      "sub_type": null,
      "first_seen": "2026-06-30T10:01:53Z",
      "last_seen": "2026-06-30T10:01:53Z",
      "dedup_hash": "9d71741cfa7c92bb"
    },
    {
      "id": "ss-lv-bmxfng",
      "source_id": "bmxfng",
      "source_domain": "ss.lv",
      "source_url": "https://www.ss.lv/msg/lv/real-estate/flats/riga/shampeteris-pleskodale/bmxfng.html",
      "type": "apartment",
      "title": "Īrei tiek piedāvāts dzīvoklis jaunajā projektā Zalves dārzs. M",
      "district": "Unknown",
      "street": "Šampēteris-Pleskodāle Zalves 37",
      "price": 1100.0,
      "price_unit": "per_month",
      "currency": "EUR",
      "rooms": 3,
      "area": 104.0,
      "floor": "2/5",
      "year": null,
      "image": "https://i.ss.lv/gallery/7/1260/314872/62974378.jpg",
      "description": "",
      "amenities": [],
      "sub_type": null,
      "first_seen": "2026-06-30T10:01:53Z",
      "last_seen": "2026-06-30T10:01:53Z",
      "dedup_hash": "05ef6d65cdb32dc2"
    },
    {
      "id": "ss-lv-ckjff",
      "source_id": "ckjff",
      "source_domain": "ss.lv",
      "source_url": "https://www.ss.lv/msg/lv/real-estate/flats/riga/bolderaya/ckjff.html",
      "type": "apartment",
      "title": "Сдается однокомнатная квартира с лоджией в Болдерае. Квартир",
      "district": "Bolderāja",
      "street": "Gobas 20/3",
      "price": 190.0,
      "price_unit": "per_month",
      "currency": "EUR",
      "rooms": 1,
      "area": 43.0,
      "floor": "7/9",
      "year": null,
      "image": "https://i.ss.lv/gallery/8/1507/376580/75315941.jpg",
      "description": "",
      "amenities": [],
      "sub_type": null,
      "first_seen": "2026-06-30T10:01:53Z",
      "last_seen": "2026-06-30T10:01:53Z",
      "dedup_hash": "af1a27a3d68b8154"
    },
    {
      "id": "ss-lv-aoilg",
      "source_id": "aoilg",
      "source_domain": "ss.lv",
      "source_url": "https://www.ss.lv/msg/lv/real-estate/flats/riga/centre/aoilg.html",
      "type": "apartment",
      "title": "Īpašnieks izīrē 3 ist. dz. 139m2. Pilnībā mēbelēts dzīvoklis.",
      "district": "Centrs",
      "street": "Čaka 59",
      "price": 990.0,
      "price_unit": "per_month",
      "currency": "EUR",
      "rooms": 3,
      "area": 139.0,
      "floor": "5/5",
      "year": null,
      "image": "https://i.ss.lv/gallery/8/1502/375289/75057628.jpg",
      "description": "",
      "amenities": [],
      "sub_type": null,
      "first_seen": "2026-06-30T10:01:53Z",
      "last_seen": "2026-06-30T10:01:53Z",
      "dedup_hash": "a2ab7060a1b3004c"
    },
    {
      "id": "ss-lv-dmbfb",
      "source_id": "dmbfb",
      "source_domain": "ss.lv",
      "source_url": "https://www.ss.lv/msg/lv/real-estate/flats/riga/centre/dmbfb.html",
      "type": "apartment",
      "title": "Ilgtermiņā tiek piedāvāts renovēts divistabu dzīvoklis pirmskara",
      "district": "Centrs",
      "street": "Matīsa 18",
      "price": 400.0,
      "price_unit": "per_month",
      "currency": "EUR",
      "rooms": 2,
      "area": 41.0,
      "floor": "3/5",
      "year": null,
      "image": "https://i.ss.lv/gallery/8/1509/377019/75403738.jpg",
      "description": "",
      "amenities": [],
      "sub_type": null,
      "first_seen": "2026-06-30T10:01:53Z",
      "last_seen": "2026-06-30T10:01:53Z",
      "dedup_hash": "7b56dab0e5938779"
    },
    {
      "id": "ss-lv-bihgo",
      "source_id": "bihgo",
      "source_domain": "ss.lv",
      "source_url": "https://www.ss.lv/msg/lv/real-estate/flats/riga/centre/bihgo.html",
      "type": "apartment",
      "title": "Ilgtermiņā tiek piedāvāts gaišs un ērts trīsistabu dzīvoklis pir",
      "district": "Centrs",
      "street": "Matīsa 18",
      "price": 560.0,
      "price_unit": "per_month",
      "currency": "EUR",
      "rooms": 3,
      "area": 77.0,
      "floor": "5/5",
      "year": null,
      "image": "https://i.ss.lv/gallery/8/1500/374893/74978562.jpg",
      "description": "",
      "amenities": [],
      "sub_type": null,
      "first_seen": "2026-06-30T10:01:53Z",
      "last_seen": "2026-06-30T10:01:53Z",
      "dedup_hash": "5587074a1f3b2e45"
    },
    {
      "id": "ss-lv-cjpfm",
      "source_id": "cjpfm",
      "source_domain": "ss.lv",
      "source_url": "https://www.ss.lv/msg/lv/real-estate/flats/riga/centre/cjpfm.html",
      "type": "apartment",
      "title": "Tiek piedāvāts trīsistabu dzīvoklis, klusā pirmskara mājā pagalm",
      "district": "Centrs",
      "street": "Čaka 117",
      "price": 520.0,
      "price_unit": "per_month",
      "currency": "EUR",
      "rooms": 3,
      "area": 70.0,
      "floor": "5/6",
      "year": null,
      "image": "https://i.ss.lv/gallery/8/1465/366043/73208518.jpg",
      "description": "",
      "amenities": [],
      "sub_type": null,
      "first_seen": "2026-06-30T10:01:53Z",
      "last_seen": "2026-06-30T10:01:53Z",
      "dedup_hash": "5c8facbecca168da"
    },
    {
      "id": "ss-lv-fxcec",
      "source_id": "fxcec",
      "source_domain": "ss.lv",
      "source_url": "https://www.ss.lv/msg/lv/real-estate/flats/riga/centre/fxcec.html",
      "type": "apartment",
      "title": "Tiek piedāvāts divistabu dzīvoklis, klusā pirmskara mājā pagalmā",
      "district": "Centrs",
      "street": "Čaka 117",
      "price": 440.0,
      "price_unit": "per_month",
      "currency": "EUR",
      "rooms": 2,
      "area": 59.0,
      "floor": "5/6",
      "year": null,
      "image": "https://i.ss.lv/gallery/8/1495/373573/74714597.jpg",
      "description": "",
      "amenities": [],
      "sub_type": null,
      "first_seen": "2026-06-30T10:01:53Z",
      "last_seen": "2026-06-30T10:01:53Z",
      "dedup_hash": "43ad3d57ac2cb5f4"
    },
    {
      "id": "ss-lv-afcog",
      "source_id": "afcog",
      "source_domain": "ss.lv",
      "source_url": "https://www.ss.lv/msg/lv/real-estate/flats/riga/kengarags/afcog.html",
      "type": "apartment",
      "title": "Tiek piedāvāts mājīgs divistabu dzīvokļis jaunbūvē Daugavas Kras",
      "district": "Ķengarags",
      "street": "Ķengaraga 10",
      "price": 420.0,
      "price_unit": "per_month",
      "currency": "EUR",
      "rooms": 2,
      "area": 36.0,
      "floor": "3/5",
      "year": null,
      "image": "https://i.ss.lv/gallery/5/957/239213/47842459.jpg",
      "description": "",
      "amenities": [],
      "sub_type": null,
      "first_seen": "2026-06-30T10:01:53Z",
      "last_seen": "2026-06-30T10:01:53Z",
      "dedup_hash": "c5824a3f1612e2d3"
    },
    {
      "id": "ss-lv-glgeg",
      "source_id": "glgeg",
      "source_domain": "ss.lv",
      "source_url": "https://www.ss.lv/msg/lv/real-estate/flats/riga/kengarags/glgeg.html",
      "type": "apartment",
      "title": "Tiek piedāvāts mājīgs divistabu dzīvokļis jaunbūvē Daugavas Kras",
      "district": "Ķengarags",
      "street": "Ķengaraga 10",
      "price": 550.0,
      "price_unit": "per_month",
      "currency": "EUR",
      "rooms": 2,
      "area": 50.0,
      "floor": "3/5",
      "year": null,
      "image": "https://i.ss.lv/gallery/8/1499/374750/74949977.jpg",
      "description": "",
      "amenities": [],
      "sub_type": null,
      "first_seen": "2026-06-30T10:01:53Z",
      "last_seen": "2026-06-30T10:01:53Z",
      "dedup_hash": "185497eec614b8d1"
    },
    {
      "id": "ss-lv-dbigf",
      "source_id": "dbigf",
      "source_domain": "ss.lv",
      "source_url": "https://www.ss.lv/msg/lv/real-estate/flats/riga/kengarags/dbigf.html",
      "type": "apartment",
      "title": "Tiek piedāvāts mājīgs divistabu dzīvokļis jaunbūvē Daugavas Kras",
      "district": "Ķengarags",
      "street": "Ķengaraga 10",
      "price": 500.0,
      "price_unit": "per_month",
      "currency": "EUR",
      "rooms": 2,
      "area": 55.0,
      "floor": "2/5",
      "year": null,
      "image": "https://i.ss.lv/gallery/5/941/235221/47044180.jpg",
      "description": "",
      "amenities": [],
      "sub_type": null,
      "first_seen": "2026-06-30T10:01:53Z",
      "last_seen": "2026-06-30T10:01:53Z",
      "dedup_hash": "a4456cf9019d9550"
    },
    {
      "id": "ss-lv-eehcf",
      "source_id": "eehcf",
      "source_domain": "ss.lv",
      "source_url": "https://www.ss.lv/msg/lv/real-estate/flats/riga/kengarags/eehcf.html",
      "type": "apartment",
      "title": "Tiek piedāvāts mājīgs divistabu dzīvokļis jaunbūvē Daugavas Kras",
      "district": "Ķengarags",
      "street": "Ķengaraga 10",
      "price": 450.0,
      "price_unit": "per_month",
      "currency": "EUR",
      "rooms": 2,
      "area": 40.0,
      "floor": "3/5",
      "year": null,
      "image": "https://i.ss.lv/gallery/7/1313/328164/65632720.jpg",
      "description": "",
      "amenities": [],
      "sub_type": null,
      "first_seen": "2026-06-30T10:01:53Z",
      "last_seen": "2026-06-30T10:01:53Z",
      "dedup_hash": "72a2c1d79243bc60"
    },
    {
      "id": "ss-lv-begdmd",
      "source_id": "begdmd",
      "source_domain": "ss.lv",
      "source_url": "https://www.ss.lv/msg/lv/real-estate/flats/riga/centre/begdmd.html",
      "type": "apartment",
      "title": "Izīrēju viesnīcas tipa, komunālajā dzīvoklī istabu, slēgta ar at",
      "district": "Centrs",
      "street": "Brīvības 52",
      "price": 180.0,
      "price_unit": "per_month",
      "currency": "EUR",
      "rooms": 1,
      "area": 14.0,
      "floor": "2/5",
      "year": null,
      "image": "https://i.ss.lv/gallery/8/1515/378695/75738939.jpg",
      "description": "",
      "amenities": [],
      "sub_type": null,
      "first_seen": "2026-06-30T10:01:53Z",
      "last_seen": "2026-06-30T10:01:53Z",
      "dedup_hash": "51bc0eb206b621d5"
    },
    {
      "id": "ss-lv-gcnoh",
      "source_id": "gcnoh",
      "source_domain": "ss.lv",
      "source_url": "https://www.ss.lv/msg/lv/real-estate/flats/riga/centre/gcnoh.html",
      "type": "apartment",
      "title": "Izīrē ilgtermiņā 1-istabas dzīvokli klusajā centrā. Silts un s",
      "district": "Centrs",
      "street": "Valdemāra 105",
      "price": 250.0,
      "price_unit": "per_month",
      "currency": "EUR",
      "rooms": 1,
      "area": 32.0,
      "floor": "3/5",
      "year": null,
      "image": "https://i.ss.lv/gallery/8/1515/378622/75724311.jpg",
      "description": "",
      "amenities": [],
      "sub_type": null,
      "first_seen": "2026-06-30T10:01:53Z",
      "last_seen": "2026-06-30T10:01:53Z",
      "dedup_hash": "77afde6b61f051f2"
    },
    {
      "id": "ss-lv-dhxdl",
      "source_id": "dhxdl",
      "source_domain": "ss.lv",
      "source_url": "https://www.ss.lv/msg/lv/real-estate/flats/riga/centre/dhxdl.html",
      "type": "apartment",
      "title": "Tiek izīrēt Istaba pilsētas centrā. Istaba aprīkota ar mēbelēm,",
      "district": "Centrs",
      "street": "Benjamiņas 23",
      "price": 250.0,
      "price_unit": "per_month",
      "currency": "EUR",
      "rooms": 1,
      "area": 18.0,
      "floor": "1/2",
      "year": null,
      "image": "https://i.ss.lv/gallery/8/1515/378694/75738716.jpg",
      "description": "",
      "amenities": [],
      "sub_type": null,
      "first_seen": "2026-06-30T10:01:53Z",
      "last_seen": "2026-06-30T10:01:53Z",
      "dedup_hash": "d0644743f15ccfae"
    },
    {
      "id": "ss-lv-cdmixk",
      "source_id": "cdmixk",
      "source_domain": "ss.lv",
      "source_url": "https://www.ss.lv/msg/lv/real-estate/flats/riga/ziepniekkalns/cdmixk.html",
      "type": "apartment",
      "title": "Izīrē gaišu 1-istabas dzīvokli Ziepniekkalnā ar lodžiju. Lab",
      "district": "Ziepniekkalns",
      "street": "Īslīces 14",
      "price": 250.0,
      "price_unit": "per_month",
      "currency": "EUR",
      "rooms": 1,
      "area": 29.0,
      "floor": "11/12",
      "year": null,
      "image": "https://i.ss.lv/gallery/8/1502/375450/75089860.jpg",
      "description": "",
      "amenities": [],
      "sub_type": null,
      "first_seen": "2026-06-30T10:01:57Z",
      "last_seen": "2026-06-30T10:01:57Z",
      "dedup_hash": "771208f1f220ca2a"
    },
    {
      "id": "ss-lv-aidhj",
      "source_id": "aidhj",
      "source_domain": "ss.lv",
      "source_url": "https://www.ss.lv/msg/lv/real-estate/flats/riga/centre/aidhj.html",
      "type": "apartment",
      "title": "Izīrē 1-istabas dzīvokli. Pieejams no 01.07.2026. Mājīgs un g",
      "district": "Centrs",
      "street": "Pērnavas 37a",
      "price": 310.0,
      "price_unit": "per_month",
      "currency": "EUR",
      "rooms": 1,
      "area": 21.0,
      "floor": "2/5",
      "year": null,
      "image": "https://i.ss.lv/gallery/8/1511/377582/75516248.jpg",
      "description": "",
      "amenities": [],
      "sub_type": null,
      "first_seen": "2026-06-30T10:01:57Z",
      "last_seen": "2026-06-30T10:01:57Z",
      "dedup_hash": "a9bbeed980aac7d3"
    },
    {
      "id": "ss-lv-iexnl",
      "source_id": "iexnl",
      "source_domain": "ss.lv",
      "source_url": "https://www.ss.lv/msg/lv/real-estate/flats/riga/teika/iexnl.html",
      "type": "apartment",
      "title": "Tiek izīrēts patīkams, daļēji mēbelēts divu izolētu istabu dzīvo",
      "district": "Teika",
      "street": "Zemgala 20",
      "price": 430.0,
      "price_unit": "per_month",
      "currency": "EUR",
      "rooms": 2,
      "area": 55.0,
      "floor": "1/3",
      "year": null,
      "image": "https://i.ss.lv/gallery/8/1515/378686/75737052.jpg",
      "description": "",
      "amenities": [],
      "sub_type": null,
      "first_seen": "2026-06-30T10:01:57Z",
      "last_seen": "2026-06-30T10:01:57Z",
      "dedup_hash": "b5d6f02235f11a1a"
    },
    {
      "id": "ss-lv-ehfbp",
      "source_id": "ehfbp",
      "source_domain": "ss.lv",
      "source_url": "https://www.ss.lv/msg/lv/real-estate/flats/riga/centre/ehfbp.html",
      "type": "apartment",
      "title": "Izīrē vienistabas dzīvokli ar brīnišķīgu skatu uz Daugavu. Dzīvo",
      "district": "Centrs",
      "street": "Lastādijas 39",
      "price": 320.0,
      "price_unit": "per_month",
      "currency": "EUR",
      "rooms": 1,
      "area": 31.0,
      "floor": "3/6",
      "year": null,
      "image": "https://i.ss.lv/gallery/8/1515/378676/75735004.jpg",
      "description": "",
      "amenities": [],
      "sub_type": null,
      "first_seen": "2026-06-30T10:01:57Z",
      "last_seen": "2026-06-30T10:01:57Z",
      "dedup_hash": "25726db4080c1465"
    },
    {
      "id": "ss-lv-cfbcmi",
      "source_id": "cfbcmi",
      "source_domain": "ss.lv",
      "source_url": "https://www.ss.lv/msg/lv/real-estate/flats/riga/ziepniekkalns/cfbcmi.html",
      "type": "apartment",
      "title": "Dzīvoklis ar pilnībā aprīkotu virtuvi un trauku mazgājamo mašīnu",
      "district": "Ziepniekkalns",
      "street": "Graudu 8",
      "price": 670.0,
      "price_unit": "per_month",
      "currency": "EUR",
      "rooms": 3,
      "area": 64.0,
      "floor": "1/5",
      "year": null,
      "image": "https://i.ss.lv/gallery/8/1515/378693/75738441.jpg",
      "description": "",
      "amenities": [],
      "sub_type": null,
      "first_seen": "2026-06-30T10:01:57Z",
      "last_seen": "2026-06-30T10:01:57Z",
      "dedup_hash": "7343c63faea77346"
    },
    {
      "id": "ss-lv-eenll",
      "source_id": "eenll",
      "source_domain": "ss.lv",
      "source_url": "https://www.ss.lv/msg/lv/real-estate/flats/riga/ilguciems/eenll.html",
      "type": "apartment",
      "title": "Izīrējam skaistu modernu dzīvokli idealā stāvoklī. Pilnībā mēbel",
      "district": "Iļģuciems",
      "street": "Lidoņu 15",
      "price": 330.0,
      "price_unit": "per_month",
      "currency": "EUR",
      "rooms": 1,
      "area": 27.0,
      "floor": "5/5",
      "year": null,
      "image": "https://i.ss.lv/gallery/8/1515/378692/75738389.jpg",
      "description": "",
      "amenities": [],
      "sub_type": null,
      "first_seen": "2026-06-30T10:01:57Z",
      "last_seen": "2026-06-30T10:01:57Z",
      "dedup_hash": "30069e6c42fc5d63"
    },
    {
      "id": "ss-lv-cghbch",
      "source_id": "cghbch",
      "source_domain": "ss.lv",
      "source_url": "https://www.ss.lv/msg/lv/real-estate/flats/riga/teika/cghbch.html",
      "type": "apartment",
      "title": "Ir pieejams īrei kopmītņu tipa dzīvoklis ar koplietošanas ērtībā",
      "district": "Teika",
      "street": "Ieriķu 48",
      "price": 130.0,
      "price_unit": "per_month",
      "currency": "EUR",
      "rooms": 1,
      "area": 20.0,
      "floor": "2/3",
      "year": null,
      "image": "https://i.ss.lv/gallery/8/1503/375628/75125472.jpg",
      "description": "",
      "amenities": [],
      "sub_type": null,
      "first_seen": "2026-06-30T10:01:57Z",
      "last_seen": "2026-06-30T10:01:57Z",
      "dedup_hash": "2ba11ce622b20c97"
    },
    {
      "id": "ss-lv-codgn",
      "source_id": "codgn",
      "source_domain": "ss.lv",
      "source_url": "https://www.ss.lv/msg/lv/real-estate/flats/riga/maskavas-priekshpilseta/codgn.html",
      "type": "apartment",
      "title": "No jūlija ilgtermiņā (minimālais termiņš 2 gadi) tiek izīrēts pl",
      "district": "Unknown",
      "street": "Latgales priekšpilsēta Krāslavas 1",
      "price": 400.0,
      "price_unit": "per_month",
      "currency": "EUR",
      "rooms": 2,
      "area": 55.0,
      "floor": "5/5",
      "year": null,
      "image": "https://i.ss.lv/gallery/8/1515/378692/75738237.jpg",
      "description": "",
      "amenities": [],
      "sub_type": null,
      "first_seen": "2026-06-30T10:01:57Z",
      "last_seen": "2026-06-30T10:01:57Z",
      "dedup_hash": "77a352f3a137010b"
    },
    {
      "id": "ss-lv-chmdp",
      "source_id": "chmdp",
      "source_domain": "ss.lv",
      "source_url": "https://www.ss.lv/msg/lv/real-estate/flats/riga/centre/chmdp.html",
      "type": "apartment",
      "title": "Ilgtermiņa īre pilsētas klusajā centrā – tieši no īpašnieka, bez",
      "district": "Centrs",
      "street": "Vīlandes 14",
      "price": 1465.0,
      "price_unit": "per_month",
      "currency": "EUR",
      "rooms": 3,
      "area": 113.0,
      "floor": "3/5",
      "year": null,
      "image": "https://i.ss.lv/gallery/8/1427/356705/71341000.jpg",
      "description": "",
      "amenities": [],
      "sub_type": null,
      "first_seen": "2026-06-30T10:01:57Z",
      "last_seen": "2026-06-30T10:01:57Z",
      "dedup_hash": "f85648707d656302"
    },
    {
      "id": "ss-lv-ghnlm",
      "source_id": "ghnlm",
      "source_domain": "ss.lv",
      "source_url": "https://www.ss.lv/msg/lv/real-estate/flats/riga/centre/ghnlm.html",
      "type": "apartment",
      "title": "Piedāvājumā pilnīgi jauns premium klases studio tipa dzīvoklis v",
      "district": "Centrs",
      "street": "Lāčplēša 36",
      "price": 600.0,
      "price_unit": "per_month",
      "currency": "EUR",
      "rooms": 1,
      "area": 29.0,
      "floor": "4/6",
      "year": null,
      "image": "https://i.ss.lv/gallery/8/1515/378681/75736111.jpg",
      "description": "",
      "amenities": [],
      "sub_type": null,
      "first_seen": "2026-06-30T10:01:57Z",
      "last_seen": "2026-06-30T10:01:57Z",
      "dedup_hash": "ab0394884689b5b3"
    },
    {
      "id": "ss-lv-beidjf",
      "source_id": "beidjf",
      "source_domain": "ss.lv",
      "source_url": "https://www.ss.lv/msg/lv/real-estate/flats/riga/centre/beidjf.html",
      "type": "apartment",
      "title": "Lieliska iespēja dzīvot Rīgas centrā – renovētā un mājīgā projek",
      "district": "Centrs",
      "street": "Stabu 87a",
      "price": 650.0,
      "price_unit": "per_month",
      "currency": "EUR",
      "rooms": 2,
      "area": 46.0,
      "floor": "2/5",
      "year": null,
      "image": "https://i.ss.lv/gallery/8/1430/357361/71472157.jpg",
      "description": "",
      "amenities": [],
      "sub_type": null,
      "first_seen": "2026-06-30T10:01:57Z",
      "last_seen": "2026-06-30T10:01:57Z",
      "dedup_hash": "ee1de086a7b2e2e8"
    },
    {
      "id": "ss-lv-cfbgkd",
      "source_id": "cfbgkd",
      "source_domain": "ss.lv",
      "source_url": "https://www.ss.lv/msg/lv/real-estate/flats/riga/maskavas-priekshpilseta/cfbgkd.html",
      "type": "apartment",
      "title": "Izīrē 2 istabu dzīvokli jaunajā projektā MF Residence, Latgales",
      "district": "Unknown",
      "street": "Latgales priekšpilsēta Latgales 131K2",
      "price": 690.0,
      "price_unit": "per_month",
      "currency": "EUR",
      "rooms": 2,
      "area": 48.0,
      "floor": "3/4",
      "year": null,
      "image": "https://i.ss.lv/gallery/8/1445/361224/72244694.jpg",
      "description": "",
      "amenities": [],
      "sub_type": null,
      "first_seen": "2026-06-30T10:01:57Z",
      "last_seen": "2026-06-30T10:01:57Z",
      "dedup_hash": "f7d305b59135afd9"
    },
    {
      "id": "ss-lv-bddmo",
      "source_id": "bddmo",
      "source_domain": "ss.lv",
      "source_url": "https://www.ss.lv/msg/lv/real-estate/flats/riga/purvciems/bddmo.html",
      "type": "apartment",
      "title": "Ilgtermiņa īrei tiek piedāvāts 2 istabu dzīvoklis Purvciemā. Dzī",
      "district": "Purvciems",
      "street": "Nīcgales 11",
      "price": 250.0,
      "price_unit": "per_month",
      "currency": "EUR",
      "rooms": 2,
      "area": 39.0,
      "floor": "2/5",
      "year": null,
      "image": "https://i.ss.lv/gallery/8/1515/378691/75738105.jpg",
      "description": "",
      "amenities": [],
      "sub_type": null,
      "first_seen": "2026-06-30T10:01:57Z",
      "last_seen": "2026-06-30T10:01:57Z",
      "dedup_hash": "a4b52804ab06f315"
    },
    {
      "id": "ss-lv-cepggf",
      "source_id": "cepggf",
      "source_domain": "ss.lv",
      "source_url": "https://www.ss.lv/msg/lv/real-estate/flats/riga/ziepniekkalns/cepggf.html",
      "type": "apartment",
      "title": "Apskatīt var tikai rīt 1. jūlijā Dzīvoklis pieejams no 2026. ga",
      "district": "Ziepniekkalns",
      "street": "Īslīces 14",
      "price": 360.0,
      "price_unit": "per_month",
      "currency": "EUR",
      "rooms": 1,
      "area": 34.0,
      "floor": "3/12",
      "year": null,
      "image": "https://i.ss.lv/gallery/8/1512/377798/75559457.jpg",
      "description": "",
      "amenities": [],
      "sub_type": null,
      "first_seen": "2026-06-30T10:01:57Z",
      "last_seen": "2026-06-30T10:01:57Z",
      "dedup_hash": "9b8deff61df14da4"
    },
    {
      "id": "ss-lv-bedxjb",
      "source_id": "bedxjb",
      "source_domain": "ss.lv",
      "source_url": "https://www.ss.lv/msg/lv/real-estate/flats/riga/centre/bedxjb.html",
      "type": "apartment",
      "title": "Jauns, kapitāli izremontēts dzīvoklis klusā iekšpagalmā. Sti",
      "district": "Centrs",
      "street": "Blaumaņa 9a",
      "price": 720.0,
      "price_unit": "per_month",
      "currency": "EUR",
      "rooms": 3,
      "area": 50.0,
      "floor": "1/5",
      "year": null,
      "image": "https://i.ss.lv/gallery/8/1515/378690/75737867.jpg",
      "description": "",
      "amenities": [],
      "sub_type": null,
      "first_seen": "2026-06-30T10:01:57Z",
      "last_seen": "2026-06-30T10:01:57Z",
      "dedup_hash": "cc06bd3dc9261dd2"
    },
    {
      "id": "ss-lv-dgppl",
      "source_id": "dgppl",
      "source_domain": "ss.lv",
      "source_url": "https://www.ss.lv/msg/lv/real-estate/flats/riga/agenskalns/dgppl.html",
      "type": "apartment",
      "title": "Tiešais īpašnieks izīrē ilgtermiņā vienistabas dzīvokli. Dzīvokl",
      "district": "Āgenskalns",
      "street": "Melnsila 19",
      "price": 290.0,
      "price_unit": "per_month",
      "currency": "EUR",
      "rooms": 1,
      "area": 30.0,
      "floor": "4/5",
      "year": null,
      "image": "https://i.ss.lv/gallery/8/1444/360850/72169920.jpg",
      "description": "",
      "amenities": [],
      "sub_type": null,
      "first_seen": "2026-06-30T10:01:57Z",
      "last_seen": "2026-06-30T10:01:57Z",
      "dedup_hash": "d9c196f3e85d768a"
    },
    {
      "id": "ss-lv-ckgcm",
      "source_id": "ckgcm",
      "source_domain": "ss.lv",
      "source_url": "https://www.ss.lv/msg/lv/real-estate/flats/riga/centre/ckgcm.html",
      "type": "apartment",
      "title": "Pagalma ēka, ieeja no ielas un pagalma, logi vērsti uz pagalma p",
      "district": "Centrs",
      "street": "Cēsu 30",
      "price": 370.0,
      "price_unit": "per_month",
      "currency": "EUR",
      "rooms": 1,
      "area": 39.0,
      "floor": "1/3",
      "year": null,
      "image": "https://i.ss.lv/gallery/8/1440/359824/71964727.jpg",
      "description": "",
      "amenities": [],
      "sub_type": null,
      "first_seen": "2026-06-30T10:01:57Z",
      "last_seen": "2026-06-30T10:01:57Z",
      "dedup_hash": "c9f75742dbfc0072"
    },
    {
      "id": "ss-lv-afkeg",
      "source_id": "afkeg",
      "source_domain": "ss.lv",
      "source_url": "https://www.ss.lv/msg/lv/real-estate/flats/riga/teika/afkeg.html",
      "type": "apartment",
      "title": "Ilgtermiņa īrei pieejams gaišs, silts 42 m² dzīvoklis 5. stāvā.",
      "district": "Teika",
      "street": "Raunas 35k2",
      "price": 450.0,
      "price_unit": "per_month",
      "currency": "EUR",
      "rooms": 2,
      "area": 42.0,
      "floor": "5/5",
      "year": null,
      "image": "https://i.ss.lv/gallery/8/1403/350504/70100752.jpg",
      "description": "",
      "amenities": [],
      "sub_type": null,
      "first_seen": "2026-06-30T10:01:57Z",
      "last_seen": "2026-06-30T10:01:57Z",
      "dedup_hash": "5be2ec0e04fa684a"
    },
    {
      "id": "ss-lv-beixng",
      "source_id": "beixng",
      "source_domain": "ss.lv",
      "source_url": "https://www.ss.lv/msg/lv/real-estate/flats/riga/centre/beixng.html",
      "type": "apartment",
      "title": "Īpašnieks ilgtermiņā izīrē mājīgu, pilnībā remontētu 5, 5 istabu",
      "district": "Centrs",
      "street": "Baznīcas 34",
      "price": 1650.0,
      "price_unit": "per_month",
      "currency": "EUR",
      "rooms": 5,
      "area": 153.0,
      "floor": "4/5",
      "year": null,
      "image": "https://i.ss.lv/gallery/8/1496/373951/74790124.jpg",
      "description": "",
      "amenities": [],
      "sub_type": null,
      "first_seen": "2026-06-30T10:01:57Z",
      "last_seen": "2026-06-30T10:01:57Z",
      "dedup_hash": "86f9529e4cb12093"
    },
    {
      "id": "ss-lv-djlkd",
      "source_id": "djlkd",
      "source_domain": "ss.lv",
      "source_url": "https://www.ss.lv/msg/lv/real-estate/flats/riga/centre/djlkd.html",
      "type": "apartment",
      "title": "Izīrē vienistabu dzīvokli ar visām ertībām, pirmais stāvs, ir pa",
      "district": "Centrs",
      "street": "Brīvības 156",
      "price": 280.0,
      "price_unit": "per_month",
      "currency": "EUR",
      "rooms": 1,
      "area": 24.0,
      "floor": "1/5",
      "year": null,
      "image": "https://i.ss.lv/gallery/8/1503/375715/75142848.jpg",
      "description": "",
      "amenities": [],
      "sub_type": null,
      "first_seen": "2026-06-30T10:01:57Z",
      "last_seen": "2026-06-30T10:01:57Z",
      "dedup_hash": "8923fa19ea0ef94c"
    },
    {
      "id": "ss-lv-emxgk",
      "source_id": "emxgk",
      "source_domain": "ss.lv",
      "source_url": "https://www.ss.lv/msg/lv/real-estate/flats/riga/yugla/emxgk.html",
      "type": "apartment",
      "title": "Īzīrē 3-istabu dzīvokli projektā Ezerjugla ar lielisku plānojumu",
      "district": "Jugla",
      "street": "Murjāņu 151",
      "price": 850.0,
      "price_unit": "per_month",
      "currency": "EUR",
      "rooms": 3,
      "area": 76.0,
      "floor": "2/4",
      "year": null,
      "image": "https://i.ss.lv/gallery/8/1489/372243/74448511.jpg",
      "description": "",
      "amenities": [],
      "sub_type": null,
      "first_seen": "2026-06-30T10:01:57Z",
      "last_seen": "2026-06-30T10:01:57Z",
      "dedup_hash": "3e97ca892c7cd11d"
    },
    {
      "id": "ss-lv-hnpfk",
      "source_id": "hnpfk",
      "source_domain": "ss.lv",
      "source_url": "https://www.ss.lv/msg/lv/real-estate/flats/riga/yugla/hnpfk.html",
      "type": "apartment",
      "title": "Īzīrē 3-istabu dzīvokli projektā Ezerjugla ar lielisku plānojumu",
      "district": "Jugla",
      "street": "Murjāņu 153",
      "price": 899.0,
      "price_unit": "per_month",
      "currency": "EUR",
      "rooms": 3,
      "area": 80.0,
      "floor": "2/4",
      "year": null,
      "image": "https://i.ss.lv/gallery/7/1316/328944/65788702.jpg",
      "description": "",
      "amenities": [],
      "sub_type": null,
      "first_seen": "2026-06-30T10:01:57Z",
      "last_seen": "2026-06-30T10:01:57Z",
      "dedup_hash": "cad0d7c25cd26d31"
    },
    {
      "id": "ss-lv-fxlip",
      "source_id": "fxlip",
      "source_domain": "ss.lv",
      "source_url": "https://www.ss.lv/msg/lv/real-estate/flats/riga/vecmilgravis/fxlip.html",
      "type": "apartment",
      "title": "Tiek izīrēts bez komisijas maksas kompakts un saulains vienistab",
      "district": "Vecmīlgrāvis",
      "street": "Skuju 29",
      "price": 260.0,
      "price_unit": "per_month",
      "currency": "EUR",
      "rooms": 1,
      "area": 20.0,
      "floor": "1/4",
      "year": null,
      "image": "https://i.ss.lv/gallery/6/1147/286629/57325767.jpg",
      "description": "",
      "amenities": [],
      "sub_type": null,
      "first_seen": "2026-06-30T10:01:57Z",
      "last_seen": "2026-06-30T10:01:57Z",
      "dedup_hash": "00774cb0d67d2f29"
    },
    {
      "id": "ss-lv-boeme",
      "source_id": "boeme",
      "source_domain": "ss.lv",
      "source_url": "https://www.ss.lv/msg/lv/real-estate/flats/riga/vecriga/boeme.html",
      "type": "apartment",
      "title": "Ilgtermiņā tiek izīrēts 5-guļamistabu dzīvoklis, labi piemērots",
      "district": "Vecrīga",
      "street": "Pils 7",
      "price": 1000.0,
      "price_unit": "per_month",
      "currency": "EUR",
      "rooms": 5,
      "area": 105.0,
      "floor": "4/5",
      "year": null,
      "image": "https://i.ss.lv/gallery/8/1487/371597/74319222.jpg",
      "description": "",
      "amenities": [],
      "sub_type": null,
      "first_seen": "2026-06-30T10:01:57Z",
      "last_seen": "2026-06-30T10:01:57Z",
      "dedup_hash": "8a527f7c451e2abb"
    },
    {
      "id": "ss-lv-beehpj",
      "source_id": "beehpj",
      "source_domain": "ss.lv",
      "source_url": "https://www.ss.lv/msg/lv/real-estate/flats/riga/centre/beehpj.html",
      "type": "apartment",
      "title": "Dzīvoklī veikts kapitālais remonts. Klusā centra daļā, zaļā ielā",
      "district": "Centrs",
      "street": "Mastu 6",
      "price": 440.0,
      "price_unit": "per_month",
      "currency": "EUR",
      "rooms": 2,
      "area": 35.0,
      "floor": "1/5",
      "year": null,
      "image": "https://i.ss.lv/gallery/7/1234/308351/61670045.jpg",
      "description": "",
      "amenities": [],
      "sub_type": null,
      "first_seen": "2026-06-30T10:01:57Z",
      "last_seen": "2026-06-30T10:01:57Z",
      "dedup_hash": "56107c963f816c84"
    },
    {
      "id": "ss-lv-fgnxf",
      "source_id": "fgnxf",
      "source_domain": "ss.lv",
      "source_url": "https://www.ss.lv/msg/lv/real-estate/flats/riga/kengarags/fgnxf.html",
      "type": "apartment",
      "title": "Сдается квартира на длительный срок(без животных)",
      "district": "Ķengarags",
      "street": "Rasas 4",
      "price": 420.0,
      "price_unit": "per_month",
      "currency": "EUR",
      "rooms": 3,
      "area": 70.0,
      "floor": "5/5",
      "year": null,
      "image": "https://i.ss.lv/gallery/8/1514/378443/75688440.jpg",
      "description": "",
      "amenities": [],
      "sub_type": null,
      "first_seen": "2026-06-30T10:01:57Z",
      "last_seen": "2026-06-30T10:01:57Z",
      "dedup_hash": "e9c350b6e50e9b6e"
    },
    {
      "id": "ss-lv-dglkn",
      "source_id": "dglkn",
      "source_domain": "ss.lv",
      "source_url": "https://www.ss.lv/msg/lv/real-estate/flats/riga/centre/dglkn.html",
      "type": "apartment",
      "title": "Īpašnieks izīrē 1-ist. dzīvoklis. Centrāla apkure, dzelzs durvis",
      "district": "Centrs",
      "street": "Sadovņikova 24",
      "price": 280.0,
      "price_unit": "per_month",
      "currency": "EUR",
      "rooms": 1,
      "area": 26.0,
      "floor": "2/5",
      "year": null,
      "image": "https://i.ss.lv/gallery/8/1512/377974/75594709.jpg",
      "description": "",
      "amenities": [],
      "sub_type": null,
      "first_seen": "2026-06-30T10:01:57Z",
      "last_seen": "2026-06-30T10:01:57Z",
      "dedup_hash": "100e1334d996cc2f"
    },
    {
      "id": "ss-lv-gpglx",
      "source_id": "gpglx",
      "source_domain": "ss.lv",
      "source_url": "https://www.ss.lv/msg/lv/real-estate/flats/riga/kengarags/gpglx.html",
      "type": "apartment",
      "title": "Высокий первый этаж. На длительный срок сдаётся современная квар",
      "district": "Ķengarags",
      "street": "Prūšu 4",
      "price": 320.0,
      "price_unit": "per_month",
      "currency": "EUR",
      "rooms": 1,
      "area": 26.0,
      "floor": "1/5",
      "year": null,
      "image": "https://i.ss.lv/gallery/8/1459/364719/72943785.jpg",
      "description": "",
      "amenities": [],
      "sub_type": null,
      "first_seen": "2026-06-30T10:01:57Z",
      "last_seen": "2026-06-30T10:01:57Z",
      "dedup_hash": "184cd2eaa68211fa"
    },
    {
      "id": "ss-lv-echgx",
      "source_id": "echgx",
      "source_domain": "ss.lv",
      "source_url": "https://www.ss.lv/msg/lv/real-estate/flats/riga/purvciems/echgx.html",
      "type": "apartment",
      "title": "Tiek izīrēts ilgtermiņā (no 1 gada) kopš 2026. gada 1. augusta.",
      "district": "Purvciems",
      "street": "Dzelzavas 68",
      "price": 600.0,
      "price_unit": "per_month",
      "currency": "EUR",
      "rooms": 2,
      "area": 53.0,
      "floor": "7/15",
      "year": null,
      "image": "https://i.ss.lv/gallery/8/1446/361308/72261408.jpg",
      "description": "",
      "amenities": [],
      "sub_type": null,
      "first_seen": "2026-06-30T10:01:57Z",
      "last_seen": "2026-06-30T10:01:57Z",
      "dedup_hash": "e11305bca8b24fbb"
    },
    {
      "id": "ss-lv-gxopi",
      "source_id": "gxopi",
      "source_domain": "ss.lv",
      "source_url": "https://www.ss.lv/msg/lv/real-estate/flats/riga/krasta-st-area/gxopi.html",
      "type": "apartment",
      "title": "Сдаётся 2-комнатная квартира. Две изолированные комнаты. Квартир",
      "district": "Unknown",
      "street": "Krasta r-ns Zilupes 6",
      "price": 320.0,
      "price_unit": "per_month",
      "currency": "EUR",
      "rooms": 2,
      "area": 50.0,
      "floor": "4/9",
      "year": null,
      "image": "https://i.ss.lv/gallery/8/1515/378678/75735407.jpg",
      "description": "",
      "amenities": [],
      "sub_type": null,
      "first_seen": "2026-06-30T10:01:57Z",
      "last_seen": "2026-06-30T10:01:57Z",
      "dedup_hash": "e3932e5e7c7c925b"
    },
    {
      "id": "ss-lv-cdnge",
      "source_id": "cdnge",
      "source_domain": "ss.lv",
      "source_url": "https://www.ss.lv/msg/lv/real-estate/flats/riga/ziepniekkalns/cdnge.html",
      "type": "apartment",
      "title": "Ilgtermiņā Izīrē Ļoti Mājīgu 2-Istabu Dzīvokli Ilgtermiņā izī",
      "district": "Ziepniekkalns",
      "street": "Ozolciema 14/1",
      "price": 500.0,
      "price_unit": "per_month",
      "currency": "EUR",
      "rooms": 2,
      "area": 64.0,
      "floor": "5/10",
      "year": null,
      "image": "https://i.ss.lv/gallery/8/1515/378678/75735416.jpg",
      "description": "",
      "amenities": [],
      "sub_type": null,
      "first_seen": "2026-06-30T10:02:01Z",
      "last_seen": "2026-06-30T10:02:01Z",
      "dedup_hash": "099d885b527df437"
    },
    {
      "id": "ss-lv-gjceh",
      "source_id": "gjceh",
      "source_domain": "ss.lv",
      "source_url": "https://www.ss.lv/msg/lv/real-estate/flats/riga/centre/gjceh.html",
      "type": "apartment",
      "title": "Сдаем просторную, светлую и теплую 1-комнатную квартиру в Центре",
      "district": "Centrs",
      "street": "Ģertrūdes 81",
      "price": 465.0,
      "price_unit": "per_month",
      "currency": "EUR",
      "rooms": 1,
      "area": 35.0,
      "floor": "2/3",
      "year": null,
      "image": "https://i.ss.lv/gallery/8/1515/378674/75734682.jpg",
      "description": "",
      "amenities": [],
      "sub_type": null,
      "first_seen": "2026-06-30T10:02:01Z",
      "last_seen": "2026-06-30T10:02:01Z",
      "dedup_hash": "aa21b644f3f104cd"
    },
    {
      "id": "ss-lv-ahxfj",
      "source_id": "ahxfj",
      "source_domain": "ss.lv",
      "source_url": "https://www.ss.lv/msg/lv/real-estate/flats/riga/vef/ahxfj.html",
      "type": "apartment",
      "title": "Sākot ar augustu ilgtermiņā tiek izīrēts 4 istabu dzīvoklis Jaun",
      "district": "Unknown",
      "street": "VEF Ropažu 14A",
      "price": 1400.0,
      "price_unit": "per_month",
      "currency": "EUR",
      "rooms": 4,
      "area": 93.0,
      "floor": "8/10",
      "year": null,
      "image": "https://i.ss.lv/gallery/8/1515/378673/75734530.jpg",
      "description": "",
      "amenities": [],
      "sub_type": null,
      "first_seen": "2026-06-30T10:02:01Z",
      "last_seen": "2026-06-30T10:02:01Z",
      "dedup_hash": "b98d63ec25e7caca"
    },
    {
      "id": "ss-lv-bjlhxg",
      "source_id": "bjlhxg",
      "source_domain": "ss.lv",
      "source_url": "https://www.ss.lv/msg/lv/real-estate/flats/riga/centre/bjlhxg.html",
      "type": "apartment",
      "title": "Īpašnieks izīrē tikko izremontētus vienistabas dzīvokļus renovēt",
      "district": "Centrs",
      "street": "Bruņinieku 115B",
      "price": 285.0,
      "price_unit": "per_month",
      "currency": "EUR",
      "rooms": 1,
      "area": 20.0,
      "floor": "5/5",
      "year": null,
      "image": "https://i.ss.lv/gallery/8/1513/378234/75646738.jpg",
      "description": "",
      "amenities": [],
      "sub_type": null,
      "first_seen": "2026-06-30T10:02:01Z",
      "last_seen": "2026-06-30T10:02:01Z",
      "dedup_hash": "751d3efbed4897fc"
    },
    {
      "id": "ss-lv-fxjki",
      "source_id": "fxjki",
      "source_domain": "ss.lv",
      "source_url": "https://www.ss.lv/msg/lv/real-estate/flats/riga/maskavas-priekshpilseta/fxjki.html",
      "type": "apartment",
      "title": "Īpašnieks izīrē 1-ist. dzīvoklis. Centrāla apkure, dzelzs durvis",
      "district": "Unknown",
      "street": "Latgales priekšpilsēta Viļānu 7",
      "price": 250.0,
      "price_unit": "per_month",
      "currency": "EUR",
      "rooms": 1,
      "area": 21.0,
      "floor": "5/5",
      "year": null,
      "image": "https://i.ss.lv/gallery/8/1505/376135/75226853.jpg",
      "description": "",
      "amenities": [],
      "sub_type": null,
      "first_seen": "2026-06-30T10:02:01Z",
      "last_seen": "2026-06-30T10:02:01Z",
      "dedup_hash": "e0b755a5b73c1bcb"
    },
    {
      "id": "ss-lv-afdhn",
      "source_id": "afdhn",
      "source_domain": "ss.lv",
      "source_url": "https://www.ss.lv/msg/lv/real-estate/flats/riga/centre/afdhn.html",
      "type": "apartment",
      "title": "Izīrēju siltu, gaišu un klusu 2 istabu dzīvokli pilsētas centrā",
      "district": "Centrs",
      "street": "Brīvības 148",
      "price": 450.0,
      "price_unit": "per_month",
      "currency": "EUR",
      "rooms": 2,
      "area": 41.0,
      "floor": "3/6",
      "year": null,
      "image": "https://i.ss.lv/gallery/8/1494/373313/74662454.jpg",
      "description": "",
      "amenities": [],
      "sub_type": null,
      "first_seen": "2026-06-30T10:02:01Z",
      "last_seen": "2026-06-30T10:02:01Z",
      "dedup_hash": "b16c4aac1af81a22"
    },
    {
      "id": "ss-lv-bebmge",
      "source_id": "bebmge",
      "source_domain": "ss.lv",
      "source_url": "https://www.ss.lv/msg/lv/real-estate/flats/riga/centre/bebmge.html",
      "type": "apartment",
      "title": "Īrei pieejams vienistabas dzīvoklis bez mēbelēm renovētā ēkā.",
      "district": "Centrs",
      "street": "Bruņinieku 121A",
      "price": 420.0,
      "price_unit": "per_month",
      "currency": "EUR",
      "rooms": 1,
      "area": 25.0,
      "floor": "5/5",
      "year": null,
      "image": "https://i.ss.lv/gallery/8/1515/378665/75732938.jpg",
      "description": "",
      "amenities": [],
      "sub_type": null,
      "first_seen": "2026-06-30T10:02:01Z",
      "last_seen": "2026-06-30T10:02:01Z",
      "dedup_hash": "ccb862685f8125cd"
    },
    {
      "id": "ss-lv-fhgpj",
      "source_id": "fhgpj",
      "source_domain": "ss.lv",
      "source_url": "https://www.ss.lv/msg/lv/real-estate/flats/riga/imanta/fhgpj.html",
      "type": "apartment",
      "title": "Сдается уютная, квартира в Иманте, современный ремонт, утеплен и",
      "district": "Imanta",
      "street": "Dammes 1",
      "price": 500.0,
      "price_unit": "per_month",
      "currency": "EUR",
      "rooms": 3,
      "area": 62.0,
      "floor": "4/9",
      "year": null,
      "image": "https://i.ss.lv/gallery/8/1515/378664/75732800.jpg",
      "description": "",
      "amenities": [],
      "sub_type": null,
      "first_seen": "2026-06-30T10:02:01Z",
      "last_seen": "2026-06-30T10:02:01Z",
      "dedup_hash": "d5188767726dd711"
    },
    {
      "id": "ss-lv-cekkpi",
      "source_id": "cekkpi",
      "source_domain": "ss.lv",
      "source_url": "https://www.ss.lv/msg/lv/real-estate/flats/riga/ziepniekkalns/cekkpi.html",
      "type": "apartment",
      "title": "Izīrē ilgtermiņā divistabu dzīvokli bez starpniekiem. Māja ene",
      "district": "Ziepniekkalns",
      "street": "Vienības g. 192",
      "price": 430.0,
      "price_unit": "per_month",
      "currency": "EUR",
      "rooms": 2,
      "area": 53.0,
      "floor": "3/5",
      "year": null,
      "image": "https://i.ss.lv/gallery/8/1515/378662/75732249.jpg",
      "description": "",
      "amenities": [],
      "sub_type": null,
      "first_seen": "2026-06-30T10:02:01Z",
      "last_seen": "2026-06-30T10:02:01Z",
      "dedup_hash": "8f2fcdfae046bbfb"
    },
    {
      "id": "ss-lv-glghg",
      "source_id": "glghg",
      "source_domain": "ss.lv",
      "source_url": "https://www.ss.lv/msg/lv/real-estate/flats/riga/kengarags/glghg.html",
      "type": "apartment",
      "title": "Сдаю 3 х комнатную квартиру на длительный срок. Рядом с торговым",
      "district": "Ķengarags",
      "street": "Bultu 3",
      "price": 400.0,
      "price_unit": "per_month",
      "currency": "EUR",
      "rooms": 3,
      "area": 70.0,
      "floor": "2/9",
      "year": null,
      "image": "https://i.ss.lv/gallery/8/1515/378662/75732334.jpg",
      "description": "",
      "amenities": [],
      "sub_type": null,
      "first_seen": "2026-06-30T10:02:01Z",
      "last_seen": "2026-06-30T10:02:01Z",
      "dedup_hash": "0d9f389fa6b45cd6"
    },
    {
      "id": "ss-lv-amddi",
      "source_id": "amddi",
      "source_domain": "ss.lv",
      "source_url": "https://www.ss.lv/msg/lv/real-estate/flats/riga/purvciems/amddi.html",
      "type": "apartment",
      "title": "No 1 jūlija izīrēju mājīgu vienistabas dzīvokli (2 stāvs), ilgte",
      "district": "Purvciems",
      "street": "Dzelzavas 59",
      "price": 350.0,
      "price_unit": "per_month",
      "currency": "EUR",
      "rooms": 1,
      "area": 32.0,
      "floor": "2/9",
      "year": null,
      "image": "https://i.ss.lv/gallery/8/1515/378659/75731792.jpg",
      "description": "",
      "amenities": [],
      "sub_type": null,
      "first_seen": "2026-06-30T10:02:01Z",
      "last_seen": "2026-06-30T10:02:01Z",
      "dedup_hash": "065f9bab74b65813"
    },
    {
      "id": "ss-lv-acclb",
      "source_id": "acclb",
      "source_domain": "ss.lv",
      "source_url": "https://www.ss.lv/msg/lv/real-estate/flats/riga/centre/acclb.html",
      "type": "apartment",
      "title": "Tiešais saimnieks izīrē vienistabas dzīvokli. Dzīvoklī ir viss p",
      "district": "Centrs",
      "street": "Valmieras 39",
      "price": 250.0,
      "price_unit": "per_month",
      "currency": "EUR",
      "rooms": 1,
      "area": 23.0,
      "floor": "3/4",
      "year": null,
      "image": "https://i.ss.lv/gallery/8/1510/377296/75459056.jpg",
      "description": "",
      "amenities": [],
      "sub_type": null,
      "first_seen": "2026-06-30T10:02:01Z",
      "last_seen": "2026-06-30T10:02:01Z",
      "dedup_hash": "8cc3b89c40eb1c05"
    },
    {
      "id": "ss-lv-hejno",
      "source_id": "hejno",
      "source_domain": "ss.lv",
      "source_url": "https://www.ss.lv/msg/lv/real-estate/flats/riga/tornjakalns/hejno.html",
      "type": "apartment",
      "title": "Сдается светлая и уютная однокомнатная квартира На длительный",
      "district": "Unknown",
      "street": "Torņakalns Garozes 11",
      "price": 220.0,
      "price_unit": "per_month",
      "currency": "EUR",
      "rooms": 1,
      "area": 38.0,
      "floor": "2/5",
      "year": null,
      "image": "https://i.ss.lv/gallery/8/1515/378657/75731352.jpg",
      "description": "",
      "amenities": [],
      "sub_type": null,
      "first_seen": "2026-06-30T10:02:01Z",
      "last_seen": "2026-06-30T10:02:01Z",
      "dedup_hash": "78740a30cfcfe3bd"
    },
    {
      "id": "ss-lv-ahomf",
      "source_id": "ahomf",
      "source_domain": "ss.lv",
      "source_url": "https://www.ss.lv/msg/lv/real-estate/flats/riga/agenskalns/ahomf.html",
      "type": "apartment",
      "title": "Izīrē gaišu, modernu un mājīgu 1 istabas dzīvokli Āgenskalnā (Āg",
      "district": "Āgenskalns",
      "street": "Āgenskalna 20",
      "price": 450.0,
      "price_unit": "per_month",
      "currency": "EUR",
      "rooms": 1,
      "area": 30.0,
      "floor": "3/5",
      "year": null,
      "image": "https://i.ss.lv/gallery/8/1515/378657/75731294.jpg",
      "description": "",
      "amenities": [],
      "sub_type": null,
      "first_seen": "2026-06-30T10:02:01Z",
      "last_seen": "2026-06-30T10:02:01Z",
      "dedup_hash": "14315f1f359ed95c"
    },
    {
      "id": "ss-lv-dpknd",
      "source_id": "dpknd",
      "source_domain": "ss.lv",
      "source_url": "https://www.ss.lv/msg/lv/real-estate/flats/riga/imanta/dpknd.html",
      "type": "apartment",
      "title": "Izīrē plašu, mājīgu un pilnībā mēbelētu 2 istabu dzīvokli projek",
      "district": "Imanta",
      "street": "Anniņmuižas 41",
      "price": 690.0,
      "price_unit": "per_month",
      "currency": "EUR",
      "rooms": 2,
      "area": 94.0,
      "floor": "15/23",
      "year": null,
      "image": "https://i.ss.lv/gallery/8/1515/378657/75731215.jpg",
      "description": "",
      "amenities": [],
      "sub_type": null,
      "first_seen": "2026-06-30T10:02:01Z",
      "last_seen": "2026-06-30T10:02:01Z",
      "dedup_hash": "1d4b96749ee136ec"
    },
    {
      "id": "ss-lv-hhiom",
      "source_id": "hhiom",
      "source_domain": "ss.lv",
      "source_url": "https://www.ss.lv/msg/lv/real-estate/flats/riga/centre/hhiom.html",
      "type": "apartment",
      "title": "Tiek izīrēts tikko izremontēts, mājīgs un funkcionāli ērts 4 ist",
      "district": "Centrs",
      "street": "Tomsona 2",
      "price": 1600.0,
      "price_unit": "per_month",
      "currency": "EUR",
      "rooms": 4,
      "area": 90.0,
      "floor": "3/5",
      "year": null,
      "image": "https://i.ss.lv/gallery/8/1497/374062/74812271.jpg",
      "description": "",
      "amenities": [],
      "sub_type": null,
      "first_seen": "2026-06-30T10:02:01Z",
      "last_seen": "2026-06-30T10:02:01Z",
      "dedup_hash": "6b0c3afc509d9497"
    },
    {
      "id": "ss-lv-eeipi",
      "source_id": "eeipi",
      "source_domain": "ss.lv",
      "source_url": "https://www.ss.lv/msg/lv/real-estate/flats/riga/zolitude/eeipi.html",
      "type": "apartment",
      "title": "Izīrē dzīvokli ar klavierēm un kondicionieri. Trīs istabas, 11",
      "district": "Zolitūde",
      "street": "Lejiņa 3",
      "price": 500.0,
      "price_unit": "per_month",
      "currency": "EUR",
      "rooms": 3,
      "area": 75.0,
      "floor": "9/9",
      "year": null,
      "image": "https://i.ss.lv/gallery/8/1515/378655/75730870.jpg",
      "description": "",
      "amenities": [],
      "sub_type": null,
      "first_seen": "2026-06-30T10:02:01Z",
      "last_seen": "2026-06-30T10:02:01Z",
      "dedup_hash": "a0cb817bb898c94f"
    },
    {
      "id": "ss-lv-cgmfxk",
      "source_id": "cgmfxk",
      "source_domain": "ss.lv",
      "source_url": "https://www.ss.lv/msg/lv/real-estate/flats/riga/teika/cgmfxk.html",
      "type": "apartment",
      "title": "Tiek izīrēts 2 istabu dzīvoklis 23m² plātībā jaunajā projektā Va",
      "district": "Teika",
      "street": "Vairoga 32",
      "price": 440.0,
      "price_unit": "per_month",
      "currency": "EUR",
      "rooms": 2,
      "area": 23.0,
      "floor": "1/3",
      "year": null,
      "image": "https://i.ss.lv/gallery/8/1515/378654/75730731.jpg",
      "description": "",
      "amenities": [],
      "sub_type": null,
      "first_seen": "2026-06-30T10:02:01Z",
      "last_seen": "2026-06-30T10:02:01Z",
      "dedup_hash": "a93bfb7acd05f258"
    },
    {
      "id": "ss-lv-hfnkp",
      "source_id": "hfnkp",
      "source_domain": "ss.lv",
      "source_url": "https://www.ss.lv/msg/lv/real-estate/flats/riga/purvciems/hfnkp.html",
      "type": "apartment",
      "title": "Izīrē 2-istabu dzīvokli (Purvciems) No 2026. gada 1. augusta uz",
      "district": "Purvciems",
      "street": "Dzelzavas 76",
      "price": 470.0,
      "price_unit": "per_month",
      "currency": "EUR",
      "rooms": 2,
      "area": 50.0,
      "floor": "4/9",
      "year": null,
      "image": "https://i.ss.lv/gallery/8/1515/378654/75730620.jpg",
      "description": "",
      "amenities": [],
      "sub_type": null,
      "first_seen": "2026-06-30T10:02:01Z",
      "last_seen": "2026-06-30T10:02:01Z",
      "dedup_hash": "225515f58c128995"
    },
    {
      "id": "ss-lv-blpfi",
      "source_id": "blpfi",
      "source_domain": "ss.lv",
      "source_url": "https://www.ss.lv/msg/lv/real-estate/flats/riga/centre/blpfi.html",
      "type": "apartment",
      "title": "Aicinām īrēt trīs istabu dzīvokli īres namā Blaumaņa ielā 5A.",
      "district": "Centrs",
      "street": "Blaumaņa 5A",
      "price": 650.0,
      "price_unit": "per_month",
      "currency": "EUR",
      "rooms": 3,
      "area": 101.0,
      "floor": "3/6",
      "year": null,
      "image": "https://i.ss.lv/gallery/8/1503/375586/75117104.jpg",
      "description": "",
      "amenities": [],
      "sub_type": null,
      "first_seen": "2026-06-30T10:02:01Z",
      "last_seen": "2026-06-30T10:02:01Z",
      "dedup_hash": "45a3457ab6031197"
    },
    {
      "id": "ss-lv-nkcoc",
      "source_id": "nkcoc",
      "source_domain": "ss.lv",
      "source_url": "https://www.ss.lv/msg/lv/real-estate/offices/riga/shampeteris-pleskodale/nkcoc.html",
      "type": "commercial",
      "title": "Īpašnieks iznomā kosmētiski izremontētas biroja telpas (4.ieeja, 1.stāvs",
      "district": "Unknown",
      "street": "",
      "price": 456.0,
      "price_unit": "per_month",
      "currency": "EUR",
      "rooms": 4,
      "area": 15.0,
      "floor": "57",
      "year": null,
      "image": "https://i.ss.lv/gallery/8/1409/352185/70436921.jpg",
      "description": "",
      "amenities": [],
      "sub_type": null,
      "first_seen": "2026-06-30T10:02:09Z",
      "last_seen": "2026-06-30T10:02:09Z",
      "dedup_hash": "7ad2d50fdc13be61"
    },
    {
      "id": "ss-lv-pbkpe",
      "source_id": "pbkpe",
      "source_domain": "ss.lv",
      "source_url": "https://www.ss.lv/msg/lv/real-estate/offices/riga/sarkandaugava/pbkpe.html",
      "type": "commercial",
      "title": "Iznomājam telpas Biznesa Parkā Dambis, Uriekstes ielā 1, Rīgā. + Lie",
      "district": "Unknown",
      "street": "",
      "price": 150.0,
      "price_unit": "per_month",
      "currency": "EUR",
      "rooms": 1,
      "area": 1.0,
      "floor": "30",
      "year": null,
      "image": "https://i.ss.lv/gallery/8/1515/378704/75740636.jpg",
      "description": "",
      "amenities": [],
      "sub_type": null,
      "first_seen": "2026-06-30T10:02:09Z",
      "last_seen": "2026-06-30T10:02:09Z",
      "dedup_hash": "89be32f8b95e431d"
    },
    {
      "id": "ss-lv-akkhf",
      "source_id": "akkhf",
      "source_domain": "ss.lv",
      "source_url": "https://www.ss.lv/msg/lv/real-estate/offices/riga/centre/akkhf.html",
      "type": "commercial",
      "title": "Nomai tiek piedāvātas gaišas telpas, plānojums sastāv no open space un v",
      "district": "Unknown",
      "street": "",
      "price": 175.0,
      "price_unit": "per_month",
      "currency": "EUR",
      "rooms": null,
      "area": 149.0,
      "floor": "34",
      "year": null,
      "image": "https://i.ss.lv/gallery/8/1511/377532/75506232.jpg",
      "description": "",
      "amenities": [],
      "sub_type": null,
      "first_seen": "2026-06-30T10:02:09Z",
      "last_seen": "2026-06-30T10:02:09Z",
      "dedup_hash": "72a2a9dc47ee23b9"
    },
    {
      "id": "ss-lv-chplj",
      "source_id": "chplj",
      "source_domain": "ss.lv",
      "source_url": "https://www.ss.lv/msg/lv/real-estate/offices/riga/centre/chplj.html",
      "type": "commercial",
      "title": "Iznomā pilnībā mēbelētu biroju Rīgas Klusajā centrā Iznomā gaišu un d",
      "district": "Unknown",
      "street": "",
      "price": 290.0,
      "price_unit": "per_month",
      "currency": "EUR",
      "rooms": null,
      "area": null,
      "floor": "19",
      "year": null,
      "image": "https://i.ss.lv/gallery/8/1426/356484/71296706.jpg",
      "description": "",
      "amenities": [],
      "sub_type": null,
      "first_seen": "2026-06-30T10:02:09Z",
      "last_seen": "2026-06-30T10:02:09Z",
      "dedup_hash": "b4792007824150ef"
    },
    {
      "id": "ss-lv-aknhf",
      "source_id": "aknhf",
      "source_domain": "ss.lv",
      "source_url": "https://www.ss.lv/msg/lv/real-estate/offices/riga/centre/aknhf.html",
      "type": "commercial",
      "title": "Iznomā biroja telpas Klijānu iela 7. 6.stāvs; Telpas platība 31, 9",
      "district": "Unknown",
      "street": "",
      "price": 160.0,
      "price_unit": "per_month",
      "currency": "EUR",
      "rooms": 7,
      "area": 7.0,
      "floor": "32",
      "year": null,
      "image": "https://i.ss.lv/gallery/8/1471/367531/73506142.jpg",
      "description": "",
      "amenities": [],
      "sub_type": null,
      "first_seen": "2026-06-30T10:02:09Z",
      "last_seen": "2026-06-30T10:02:09Z",
      "dedup_hash": "3408b5c90ce36067"
    },
    {
      "id": "ss-lv-bbdcef",
      "source_id": "bbdcef",
      "source_domain": "ss.lv",
      "source_url": "https://www.ss.lv/msg/lv/real-estate/offices/riga/vef/bbdcef.html",
      "type": "commercial",
      "title": "Tiek iznomātas gaišas atvērtā tipa biroja telpas Brīvības gatvē 214B. Te",
      "district": "Unknown",
      "street": "",
      "price": 896.0,
      "price_unit": "per_month",
      "currency": "EUR",
      "rooms": 214,
      "area": 214.0,
      "floor": "112",
      "year": null,
      "image": "https://i.ss.lv/gallery/8/1511/377718/75543493.jpg",
      "description": "",
      "amenities": [],
      "sub_type": null,
      "first_seen": "2026-06-30T10:02:09Z",
      "last_seen": "2026-06-30T10:02:09Z",
      "dedup_hash": "1522820bc1c33be3"
    },
    {
      "id": "ss-lv-beoodf",
      "source_id": "beoodf",
      "source_domain": "ss.lv",
      "source_url": "https://www.ss.lv/msg/lv/real-estate/offices/riga/purvciems/beoodf.html",
      "type": "commercial",
      "title": "Īpašnieks iznomā telpas blakus t/c Domina, Ieriķu ielā 15. Telpas atr",
      "district": "Unknown",
      "street": "",
      "price": 290.0,
      "price_unit": "per_month",
      "currency": "EUR",
      "rooms": 15,
      "area": 15.0,
      "floor": "48",
      "year": null,
      "image": "https://i.ss.lv/gallery/8/1420/354959/70991749.jpg",
      "description": "",
      "amenities": [],
      "sub_type": null,
      "first_seen": "2026-06-30T10:02:09Z",
      "last_seen": "2026-06-30T10:02:09Z",
      "dedup_hash": "2431f6a22b4413a5"
    },
    {
      "id": "ss-lv-bdiol",
      "source_id": "bdiol",
      "source_domain": "ss.lv",
      "source_url": "https://www.ss.lv/msg/lv/real-estate/offices/riga/centre/bdiol.html",
      "type": "commercial",
      "title": "Telpas nomai no īpašnieka Brīvības ielā 46-46. Papildus informācija piel",
      "district": "Unknown",
      "street": "",
      "price": 550.0,
      "price_unit": "per_month",
      "currency": "EUR",
      "rooms": 46,
      "area": 46.0,
      "floor": "86",
      "year": null,
      "image": "https://i.ss.lv/gallery/8/1459/364589/72917800.jpg",
      "description": "",
      "amenities": [],
      "sub_type": null,
      "first_seen": "2026-06-30T10:02:09Z",
      "last_seen": "2026-06-30T10:02:09Z",
      "dedup_hash": "f2e57793e516f26c"
    },
    {
      "id": "ss-lv-kdbof",
      "source_id": "kdbof",
      "source_domain": "ss.lv",
      "source_url": "https://www.ss.lv/msg/lv/real-estate/offices/riga/plyavnieki/kdbof.html",
      "type": "commercial",
      "title": "Izīrēju ofisu 20m2 cenā viss iekļauts - komunālie maksājumi un apsaimnie",
      "district": "Unknown",
      "street": "",
      "price": 150.0,
      "price_unit": "per_month",
      "currency": "EUR",
      "rooms": 20,
      "area": 6.0,
      "floor": "20",
      "year": null,
      "image": "https://i.ss.lv/gallery/7/1330/332383/66476491.jpg",
      "description": "",
      "amenities": [],
      "sub_type": null,
      "first_seen": "2026-06-30T10:02:09Z",
      "last_seen": "2026-06-30T10:02:09Z",
      "dedup_hash": "ddc7dade9a8727d8"
    },
    {
      "id": "ss-lv-cjggf",
      "source_id": "cjggf",
      "source_domain": "ss.lv",
      "source_url": "https://www.ss.lv/msg/lv/real-estate/offices/riga/centre/cjggf.html",
      "type": "commercial",
      "title": "Tiek piedāvātas nomai 1.stāva telpas, ieeja no biroja ēkas vestibila. Pā",
      "district": "Unknown",
      "street": "",
      "price": 234.0,
      "price_unit": "per_month",
      "currency": "EUR",
      "rooms": 1,
      "area": 149.0,
      "floor": "52",
      "year": null,
      "image": "https://i.ss.lv/gallery/7/1224/305885/61176804.jpg",
      "description": "",
      "amenities": [],
      "sub_type": null,
      "first_seen": "2026-06-30T10:02:09Z",
      "last_seen": "2026-06-30T10:02:09Z",
      "dedup_hash": "c4ac1061bcc0c9ae"
    },
    {
      "id": "ss-lv-ajxil",
      "source_id": "ajxil",
      "source_domain": "ss.lv",
      "source_url": "https://www.ss.lv/msg/lv/real-estate/offices/riga/agenskalns/ajxil.html",
      "type": "commercial",
      "title": "Iespējams pieslēgt izlietni. Nomai tiek piedāvātas 1.stāva telpas ar pla",
      "district": "Unknown",
      "street": "",
      "price": 450.0,
      "price_unit": "per_month",
      "currency": "EUR",
      "rooms": 1,
      "area": 11.0,
      "floor": "45",
      "year": null,
      "image": "https://i.ss.lv/gallery/8/1489/372243/74448532.jpg",
      "description": "",
      "amenities": [],
      "sub_type": null,
      "first_seen": "2026-06-30T10:02:09Z",
      "last_seen": "2026-06-30T10:02:09Z",
      "dedup_hash": "fd19e41ab3666f0f"
    },
    {
      "id": "ss-lv-dgdef",
      "source_id": "dgdef",
      "source_domain": "ss.lv",
      "source_url": "https://www.ss.lv/msg/lv/real-estate/offices/riga/centre/dgdef.html",
      "type": "commercial",
      "title": "Iznomā 1.stāva fasādes telpas mūsdienīgā biroju ēkā Ernesta Birnieka-Upī",
      "district": "Unknown",
      "street": "",
      "price": 3096.0,
      "price_unit": "per_month",
      "currency": "EUR",
      "rooms": 1,
      "area": 21.0,
      "floor": "258",
      "year": null,
      "image": "https://i.ss.lv/gallery/7/1206/301421/60284033.jpg",
      "description": "",
      "amenities": [],
      "sub_type": null,
      "first_seen": "2026-06-30T10:02:09Z",
      "last_seen": "2026-06-30T10:02:09Z",
      "dedup_hash": "025a6774df1fba78"
    },
    {
      "id": "ss-lv-hmgge",
      "source_id": "hmgge",
      "source_domain": "ss.lv",
      "source_url": "https://www.ss.lv/msg/lv/real-estate/offices/riga/centre/hmgge.html",
      "type": "commercial",
      "title": "Iznomā biroja Elizabetes ielā 31, 3.stāvā, ir lifts. Platība 28.5m2.Noma",
      "district": "Unknown",
      "street": "",
      "price": 285.0,
      "price_unit": "per_month",
      "currency": "EUR",
      "rooms": 31,
      "area": 31.0,
      "floor": "28",
      "year": null,
      "image": "https://i.ss.lv/gallery/8/1453/363080/72615986.jpg",
      "description": "",
      "amenities": [],
      "sub_type": null,
      "first_seen": "2026-06-30T10:02:09Z",
      "last_seen": "2026-06-30T10:02:09Z",
      "dedup_hash": "8dc53c136e1aafe7"
    },
    {
      "id": "ss-lv-ehoff",
      "source_id": "ehoff",
      "source_domain": "ss.lv",
      "source_url": "https://www.ss.lv/msg/lv/real-estate/offices/riga/centre/ehoff.html",
      "type": "commercial",
      "title": "Iznomā ekskluzīvu biroju ar terasi, jaunā biroju centrā, Ģetrūdes ielā 6",
      "district": "Unknown",
      "street": "",
      "price": 2069.0,
      "price_unit": "per_month",
      "currency": "EUR",
      "rooms": 6,
      "area": 66.0,
      "floor": "262",
      "year": null,
      "image": "https://i.ss.lv/gallery/8/1500/374956/74991020.jpg",
      "description": "",
      "amenities": [],
      "sub_type": null,
      "first_seen": "2026-06-30T10:02:13Z",
      "last_seen": "2026-06-30T10:02:13Z",
      "dedup_hash": "1bf3ed6673a33368"
    },
    {
      "id": "ss-lv-bjglb",
      "source_id": "bjglb",
      "source_domain": "ss.lv",
      "source_url": "https://www.ss.lv/msg/lv/real-estate/offices/riga/biekensala/bjglb.html",
      "type": "commercial",
      "title": "17.7 m² birojs nomai Mūkusalas ielā Upmalas Biroji 1 autostāvvieta iekļa",
      "district": "Unknown",
      "street": "",
      "price": 380.0,
      "price_unit": "per_month",
      "currency": "EUR",
      "rooms": 17,
      "area": 101.0,
      "floor": "18",
      "year": null,
      "image": "https://i.ss.lv/gallery/8/1512/377782/75556314.jpg",
      "description": "",
      "amenities": [],
      "sub_type": null,
      "first_seen": "2026-06-30T10:02:13Z",
      "last_seen": "2026-06-30T10:02:13Z",
      "dedup_hash": "e68c73a34f055388"
    },
    {
      "id": "ss-lv-aejgj",
      "source_id": "aejgj",
      "source_domain": "ss.lv",
      "source_url": "https://www.ss.lv/msg/lv/real-estate/offices/riga/centre/aejgj.html",
      "type": "commercial",
      "title": "54 m² birojs nomai Skanstē Ofiss S27 biznesa centrā Komunālie maksājumi",
      "district": "Unknown",
      "street": "",
      "price": 1045.0,
      "price_unit": "per_month",
      "currency": "EUR",
      "rooms": 54,
      "area": 27.0,
      "floor": "54",
      "year": null,
      "image": "https://i.ss.lv/gallery/8/1512/377780/75555827.jpg",
      "description": "",
      "amenities": [],
      "sub_type": null,
      "first_seen": "2026-06-30T10:02:13Z",
      "last_seen": "2026-06-30T10:02:13Z",
      "dedup_hash": "aaf31ac3ce084576"
    },
    {
      "id": "ss-lv-jebpo",
      "source_id": "jebpo",
      "source_domain": "ss.lv",
      "source_url": "https://www.ss.lv/msg/lv/real-estate/offices/riga/teika/jebpo.html",
      "type": "commercial",
      "title": "Iznomā plašas un gaišas mūsdienīgi funkcionālas telpas modernā ēkā \"Soun",
      "district": "Unknown",
      "street": "",
      "price": 767.0,
      "price_unit": "per_month",
      "currency": "EUR",
      "rooms": null,
      "area": 34.0,
      "floor": "118",
      "year": null,
      "image": "https://i.ss.lv/gallery/8/1505/376007/75201361.jpg",
      "description": "",
      "amenities": [],
      "sub_type": null,
      "first_seen": "2026-06-30T10:02:13Z",
      "last_seen": "2026-06-30T10:02:13Z",
      "dedup_hash": "c126af5a1e48d1aa"
    },
    {
      "id": "ss-lv-ajbbm",
      "source_id": "ajbbm",
      "source_domain": "ss.lv",
      "source_url": "https://www.ss.lv/msg/lv/real-estate/offices/riga/agenskalns/ajbbm.html",
      "type": "commercial",
      "title": "Skati līdz horizontam rada vidi, kurā idejas dzimst brīvi un netraucēti.",
      "district": "Unknown",
      "street": "",
      "price": 830.0,
      "price_unit": "per_month",
      "currency": "EUR",
      "rooms": null,
      "area": 15.0,
      "floor": "93",
      "year": null,
      "image": "https://i.ss.lv/gallery/8/1462/365279/73055788.jpg",
      "description": "",
      "amenities": [],
      "sub_type": null,
      "first_seen": "2026-06-30T10:02:13Z",
      "last_seen": "2026-06-30T10:02:13Z",
      "dedup_hash": "e77ce114049ab4de"
    },
    {
      "id": "ss-lv-ocpip",
      "source_id": "ocpip",
      "source_domain": "ss.lv",
      "source_url": "https://www.ss.lv/msg/lv/real-estate/offices/riga/teika/ocpip.html",
      "type": "commercial",
      "title": "Pieejamas gaišas biroja telpas industriālā stilā. Telpās ir gan izolēt",
      "district": "Unknown",
      "street": "",
      "price": 1215.0,
      "price_unit": "per_month",
      "currency": "EUR",
      "rooms": null,
      "area": 214.0,
      "floor": "203",
      "year": null,
      "image": "https://i.ss.lv/gallery/8/1500/374852/74970342.jpg",
      "description": "",
      "amenities": [],
      "sub_type": null,
      "first_seen": "2026-06-30T10:02:13Z",
      "last_seen": "2026-06-30T10:02:13Z",
      "dedup_hash": "e88870fdb829a485"
    },
    {
      "id": "ss-lv-fhfpx",
      "source_id": "fhfpx",
      "source_domain": "ss.lv",
      "source_url": "https://www.ss.lv/msg/lv/real-estate/offices/riga/centre/fhfpx.html",
      "type": "commercial",
      "title": "Uz nomu pieejams plašs birojs Valdemāra ielā. Ļoti labs plānojums un mie",
      "district": "Unknown",
      "street": "",
      "price": 870.0,
      "price_unit": "per_month",
      "currency": "EUR",
      "rooms": null,
      "area": 18.0,
      "floor": "87",
      "year": null,
      "image": "https://i.ss.lv/gallery/8/1515/378584/75716668.jpg",
      "description": "",
      "amenities": [],
      "sub_type": null,
      "first_seen": "2026-06-30T10:02:13Z",
      "last_seen": "2026-06-30T10:02:13Z",
      "dedup_hash": "cc9c5aebb8ad5c9a"
    },
    {
      "id": "ss-lv-ncijh",
      "source_id": "ncijh",
      "source_domain": "ss.lv",
      "source_url": "https://www.ss.lv/msg/lv/real-estate/offices/riga/centre/ncijh.html",
      "type": "commercial",
      "title": "Gaišs, saulains Birojs ar Lielisku atrašanās vietu pilsētas centrā. Blak",
      "district": "Unknown",
      "street": "",
      "price": 1600.0,
      "price_unit": "per_month",
      "currency": "EUR",
      "rooms": null,
      "area": 11.0,
      "floor": "210",
      "year": null,
      "image": "https://i.ss.lv/gallery/7/1232/307919/61583762.jpg",
      "description": "",
      "amenities": [],
      "sub_type": null,
      "first_seen": "2026-06-30T10:02:13Z",
      "last_seen": "2026-06-30T10:02:13Z",
      "dedup_hash": "5fd9ef79d9cde109"
    },
    {
      "id": "ss-lv-lffpp",
      "source_id": "lffpp",
      "source_domain": "ss.lv",
      "source_url": "https://www.ss.lv/msg/lv/real-estate/offices/riga/yugla/lffpp.html",
      "type": "commercial",
      "title": "Iznomā pilnībā aprīkotas medicīnas telpas, mūsdienīgā piecu stāvu medicī",
      "district": "Unknown",
      "street": "",
      "price": 2700.0,
      "price_unit": "per_month",
      "currency": "EUR",
      "rooms": null,
      "area": 410.0,
      "floor": "225",
      "year": null,
      "image": "https://i.ss.lv/gallery/8/1500/374869/74973792.jpg",
      "description": "",
      "amenities": [],
      "sub_type": null,
      "first_seen": "2026-06-30T10:02:13Z",
      "last_seen": "2026-06-30T10:02:13Z",
      "dedup_hash": "ad747afd09d19f7a"
    },
    {
      "id": "ss-lv-ohebe",
      "source_id": "ohebe",
      "source_domain": "ss.lv",
      "source_url": "https://www.ss.lv/msg/lv/real-estate/offices/riga/purvciems/ohebe.html",
      "type": "commercial",
      "title": "Nomai pieejamas plašas un funkcionālas biroja telpas Rīgas Industriālā p",
      "district": "Unknown",
      "street": "",
      "price": 3185.0,
      "price_unit": "per_month",
      "currency": "EUR",
      "rooms": null,
      "area": 120.0,
      "floor": "325",
      "year": null,
      "image": "https://i.ss.lv/gallery/4/674/168422/33684311.jpg",
      "description": "",
      "amenities": [],
      "sub_type": null,
      "first_seen": "2026-06-30T10:02:13Z",
      "last_seen": "2026-06-30T10:02:13Z",
      "dedup_hash": "0d46eb068c4db087"
    },
    {
      "id": "ss-lv-aheek",
      "source_id": "aheek",
      "source_domain": "ss.lv",
      "source_url": "https://www.ss.lv/msg/lv/real-estate/offices/riga/centre/aheek.html",
      "type": "commercial",
      "title": "Iznomā mūsdienīgas telpas, industriālā rajonā Eksporta ielā 12 Telpām v",
      "district": "Unknown",
      "street": "",
      "price": 640.0,
      "price_unit": "per_month",
      "currency": "EUR",
      "rooms": 12,
      "area": 12.0,
      "floor": "160",
      "year": null,
      "image": "https://i.ss.lv/gallery/8/1485/371116/74223002.jpg",
      "description": "",
      "amenities": [],
      "sub_type": null,
      "first_seen": "2026-06-30T10:02:13Z",
      "last_seen": "2026-06-30T10:02:13Z",
      "dedup_hash": "296e9074727f69c6"
    },
    {
      "id": "ss-lv-djjbh",
      "source_id": "djjbh",
      "source_domain": "ss.lv",
      "source_url": "https://www.ss.lv/msg/lv/real-estate/offices/riga/centre/djjbh.html",
      "type": "commercial",
      "title": "Iznomā gaišas telpas priekš deju, sporta nodarbībām Lāčplēša ielā 125 P",
      "district": "Unknown",
      "street": "",
      "price": 1680.0,
      "price_unit": "per_month",
      "currency": "EUR",
      "rooms": 125,
      "area": 125.0,
      "floor": "240",
      "year": null,
      "image": "https://i.ss.lv/gallery/8/1515/378612/75722320.jpg",
      "description": "",
      "amenities": [],
      "sub_type": null,
      "first_seen": "2026-06-30T10:02:13Z",
      "last_seen": "2026-06-30T10:02:13Z",
      "dedup_hash": "5ad9fcfceae60e2f"
    },
    {
      "id": "ss-lv-hndlx",
      "source_id": "hndlx",
      "source_domain": "ss.lv",
      "source_url": "https://www.ss.lv/msg/lv/real-estate/offices/riga/centre/hndlx.html",
      "type": "commercial",
      "title": "Komerctelpas nomai – Martas iela 37, Rīga Tiek iznomātas gaišas un repr",
      "district": "Unknown",
      "street": "",
      "price": 550.0,
      "price_unit": "per_month",
      "currency": "EUR",
      "rooms": 37,
      "area": 37.0,
      "floor": "27",
      "year": null,
      "image": "https://i.ss.lv/gallery/8/1515/378625/75724808.jpg",
      "description": "",
      "amenities": [],
      "sub_type": null,
      "first_seen": "2026-06-30T10:02:13Z",
      "last_seen": "2026-06-30T10:02:13Z",
      "dedup_hash": "ef3000523f66f8ae"
    },
    {
      "id": "ss-lv-bipxk",
      "source_id": "bipxk",
      "source_domain": "ss.lv",
      "source_url": "https://www.ss.lv/msg/lv/real-estate/offices/riga/imanta/bipxk.html",
      "type": "commercial",
      "title": "Iznomā ofisa telpas pilnībā mēbelētu ar kopējo platību 227m2. Visas pils",
      "district": "Unknown",
      "street": "",
      "price": 2270.0,
      "price_unit": "per_month",
      "currency": "EUR",
      "rooms": 227,
      "area": 31.0,
      "floor": "227",
      "year": null,
      "image": "https://i.ss.lv/gallery/7/1299/324652/64930366.jpg",
      "description": "",
      "amenities": [],
      "sub_type": null,
      "first_seen": "2026-06-30T10:02:13Z",
      "last_seen": "2026-06-30T10:02:13Z",
      "dedup_hash": "a1abbdd474b3a438"
    },
    {
      "id": "ss-lv-bnikc",
      "source_id": "bnikc",
      "source_domain": "ss.lv",
      "source_url": "https://www.ss.lv/msg/lv/real-estate/offices/riga/centre/bnikc.html",
      "type": "commercial",
      "title": "1.Stāvs. Īpašnieks iznomā B kategorijas biroja telpas komerckompleksa tr",
      "district": "Unknown",
      "street": "",
      "price": 120.0,
      "price_unit": "per_month",
      "currency": "EUR",
      "rooms": 1,
      "area": 40.0,
      "floor": "23",
      "year": null,
      "image": "https://i.ss.lv/gallery/6/1042/260362/52072332.jpg",
      "description": "",
      "amenities": [],
      "sub_type": null,
      "first_seen": "2026-06-30T10:02:13Z",
      "last_seen": "2026-06-30T10:02:13Z",
      "dedup_hash": "b78e6f3df3a44f9c"
    },
    {
      "id": "ss-lv-afdxh",
      "source_id": "afdxh",
      "source_domain": "ss.lv",
      "source_url": "https://www.ss.lv/msg/lv/real-estate/offices/riga/teika/afdxh.html",
      "type": "commercial",
      "title": "Alfa. Nomai tiek piedāvātas biroja telpas 56 kv. m. blakus T/c Akropole",
      "district": "Unknown",
      "street": "",
      "price": 390.0,
      "price_unit": "per_month",
      "currency": "EUR",
      "rooms": 56,
      "area": 1.0,
      "floor": "56",
      "year": null,
      "image": "https://i.ss.lv/gallery/8/1443/360622/72124295.jpg",
      "description": "",
      "amenities": [],
      "sub_type": null,
      "first_seen": "2026-06-30T10:02:13Z",
      "last_seen": "2026-06-30T10:02:13Z",
      "dedup_hash": "d9190b349db37458"
    },
    {
      "id": "ss-lv-djnee",
      "source_id": "djnee",
      "source_domain": "ss.lv",
      "source_url": "https://www.ss.lv/msg/lv/real-estate/offices/riga/darzciems/djnee.html",
      "type": "commercial",
      "title": "Iznomā biroju telpas „Dārzciema Biroji” biznesa centrā Dārzciema ielā 60",
      "district": "Unknown",
      "street": "",
      "price": 228.0,
      "price_unit": "per_month",
      "currency": "EUR",
      "rooms": 60,
      "area": 60.0,
      "floor": "19",
      "year": null,
      "image": "https://i.ss.lv/gallery/5/980/244753/48950578.jpg",
      "description": "",
      "amenities": [],
      "sub_type": null,
      "first_seen": "2026-06-30T10:02:13Z",
      "last_seen": "2026-06-30T10:02:13Z",
      "dedup_hash": "f82fd7682276474e"
    },
    {
      "id": "ss-lv-nfbmm",
      "source_id": "nfbmm",
      "source_domain": "ss.lv",
      "source_url": "https://www.ss.lv/msg/lv/real-estate/offices/riga/centre/nfbmm.html",
      "type": "commercial",
      "title": "100 darba vietas. Plānojums - kabinetu un openspace kombinācija, pārrunu",
      "district": "Unknown",
      "street": "",
      "price": 12736.0,
      "price_unit": "per_month",
      "currency": "EUR",
      "rooms": 100,
      "area": 50.0,
      "floor": "1213",
      "year": null,
      "image": "https://i.ss.lv/gallery/8/1505/376028/75205518.jpg",
      "description": "",
      "amenities": [],
      "sub_type": null,
      "first_seen": "2026-06-30T10:02:13Z",
      "last_seen": "2026-06-30T10:02:13Z",
      "dedup_hash": "94fe4d34cb003914"
    },
    {
      "id": "ss-lv-hmpjc",
      "source_id": "hmpjc",
      "source_domain": "ss.lv",
      "source_url": "https://www.ss.lv/msg/lv/real-estate/offices/riga/tornjakalns/hmpjc.html",
      "type": "commercial",
      "title": "Samazināta nomas maksa pirmajam nomas gadam. Nomai tiek piedāvātas 1.stā",
      "district": "Unknown",
      "street": "",
      "price": 490.0,
      "price_unit": "per_month",
      "currency": "EUR",
      "rooms": 1,
      "area": 33.0,
      "floor": "86",
      "year": null,
      "image": "https://i.ss.lv/gallery/7/1335/333735/66746920.jpg",
      "description": "",
      "amenities": [],
      "sub_type": null,
      "first_seen": "2026-06-30T10:02:13Z",
      "last_seen": "2026-06-30T10:02:13Z",
      "dedup_hash": "76b0a5e734a6b587"
    },
    {
      "id": "ss-lv-enhmp",
      "source_id": "enhmp",
      "source_domain": "ss.lv",
      "source_url": "https://www.ss.lv/msg/lv/real-estate/offices/riga/centre/enhmp.html",
      "type": "commercial",
      "title": "Iznomā mūsdienīgas biroja telpas biznesa centrā, Tērbatas ielā 14 Kopēj",
      "district": "Unknown",
      "street": "",
      "price": 1986.0,
      "price_unit": "per_month",
      "currency": "EUR",
      "rooms": 14,
      "area": 14.0,
      "floor": "181",
      "year": null,
      "image": "https://i.ss.lv/gallery/8/1486/371364/74272754.jpg",
      "description": "",
      "amenities": [],
      "sub_type": null,
      "first_seen": "2026-06-30T10:02:13Z",
      "last_seen": "2026-06-30T10:02:13Z",
      "dedup_hash": "4782cdd0f470936b"
    },
    {
      "id": "ss-lv-bcpbkn",
      "source_id": "bcpbkn",
      "source_domain": "ss.lv",
      "source_url": "https://www.ss.lv/msg/lv/real-estate/offices/riga/teika/bcpbkn.html",
      "type": "commercial",
      "title": "Domina Shopping tirdzniecības centrs piedāvā biroju platības. Atroda",
      "district": "Unknown",
      "street": "",
      "price": 2500.0,
      "price_unit": "per_month",
      "currency": "EUR",
      "rooms": null,
      "area": 3.0,
      "floor": "230",
      "year": null,
      "image": "https://i.ss.lv/gallery/8/1515/378601/75720008.jpg",
      "description": "",
      "amenities": [],
      "sub_type": null,
      "first_seen": "2026-06-30T10:02:13Z",
      "last_seen": "2026-06-30T10:02:13Z",
      "dedup_hash": "dbd002635ce26e68"
    },
    {
      "id": "ss-lv-ajkhg",
      "source_id": "ajkhg",
      "source_domain": "ss.lv",
      "source_url": "https://www.ss.lv/msg/lv/real-estate/offices/riga/centre/ajkhg.html",
      "type": "commercial",
      "title": "Iznomā biroja telpas E. Benjamiņas ielā 13 Telpas atrodas Benjamiņas Mī",
      "district": "Unknown",
      "street": "",
      "price": 1860.0,
      "price_unit": "per_month",
      "currency": "EUR",
      "rooms": 13,
      "area": 13.0,
      "floor": "155",
      "year": null,
      "image": "https://i.ss.lv/gallery/8/1485/371239/74247689.jpg",
      "description": "",
      "amenities": [],
      "sub_type": null,
      "first_seen": "2026-06-30T10:02:17Z",
      "last_seen": "2026-06-30T10:02:17Z",
      "dedup_hash": "2b2449ca2b06527a"
    },
    {
      "id": "ss-lv-npfik",
      "source_id": "npfik",
      "source_domain": "ss.lv",
      "source_url": "https://www.ss.lv/msg/lv/real-estate/offices/riga/bierini/npfik.html",
      "type": "commercial",
      "title": "Iznomā plašu komercplatību Rīgā, Laidzes ielā 10. Zaļa apkārtne, vairāk",
      "district": "Unknown",
      "street": "",
      "price": 850.0,
      "price_unit": "per_month",
      "currency": "EUR",
      "rooms": 10,
      "area": 10.0,
      "floor": "124",
      "year": null,
      "image": "https://i.ss.lv/gallery/8/1450/362305/72460912.jpg",
      "description": "",
      "amenities": [],
      "sub_type": null,
      "first_seen": "2026-06-30T10:02:17Z",
      "last_seen": "2026-06-30T10:02:17Z",
      "dedup_hash": "a8049333fe4a971b"
    },
    {
      "id": "ss-lv-akcgh",
      "source_id": "akcgh",
      "source_domain": "ss.lv",
      "source_url": "https://www.ss.lv/msg/lv/real-estate/offices/riga/centre/akcgh.html",
      "type": "commercial",
      "title": "Iznomā gaišas, plašas biroja telpas Ganību dambī 7a Platība – 220 kv. m",
      "district": "Unknown",
      "street": "",
      "price": 1440.0,
      "price_unit": "per_month",
      "currency": "EUR",
      "rooms": 7,
      "area": null,
      "floor": "220",
      "year": null,
      "image": "https://i.ss.lv/gallery/8/1423/355586/71117103.jpg",
      "description": "",
      "amenities": [],
      "sub_type": null,
      "first_seen": "2026-06-30T10:02:17Z",
      "last_seen": "2026-06-30T10:02:17Z",
      "dedup_hash": "5253cf0aaa73026a"
    },
    {
      "id": "ss-lv-blmpdx",
      "source_id": "blmpdx",
      "source_domain": "ss.lv",
      "source_url": "https://www.ss.lv/msg/lv/real-estate/offices/riga/darzciems/blmpdx.html",
      "type": "commercial",
      "title": "Iznomā biroja telpas: 2.stavs – 77, 3 m2 (3 istabas, virtuve un san. mez",
      "district": "Unknown",
      "street": "",
      "price": 390.0,
      "price_unit": "per_month",
      "currency": "EUR",
      "rooms": 2,
      "area": 30.0,
      "floor": "77",
      "year": null,
      "image": "https://i.ss.lv/gallery/7/1390/347360/69471840.jpg",
      "description": "",
      "amenities": [],
      "sub_type": null,
      "first_seen": "2026-06-30T10:02:17Z",
      "last_seen": "2026-06-30T10:02:17Z",
      "dedup_hash": "26c3e57c19ed2756"
    },
    {
      "id": "ss-lv-blngc",
      "source_id": "blngc",
      "source_domain": "ss.lv",
      "source_url": "https://www.ss.lv/msg/lv/real-estate/offices/riga/centre/blngc.html",
      "type": "commercial",
      "title": "Biroja Virtuālo tūri varat apskatīt mūsu mājaslapā, atverot sludinājuma",
      "district": "Unknown",
      "street": "",
      "price": 1090.0,
      "price_unit": "per_month",
      "currency": "EUR",
      "rooms": null,
      "area": 171.0,
      "floor": "109",
      "year": null,
      "image": "https://i.ss.lv/gallery/7/1350/337400/67479846.jpg",
      "description": "",
      "amenities": [],
      "sub_type": null,
      "first_seen": "2026-06-30T10:02:17Z",
      "last_seen": "2026-06-30T10:02:17Z",
      "dedup_hash": "143730ab105f991d"
    },
    {
      "id": "ss-lv-hnfdl",
      "source_id": "hnfdl",
      "source_domain": "ss.lv",
      "source_url": "https://www.ss.lv/msg/lv/real-estate/offices/riga/centre/hnfdl.html",
      "type": "commercial",
      "title": "60 darba vietas. Plānojums - kabinetu un openspace kombinācija, pārrunu",
      "district": "Unknown",
      "street": "",
      "price": 10143.0,
      "price_unit": "per_month",
      "currency": "EUR",
      "rooms": 60,
      "area": 3.0,
      "floor": "882",
      "year": null,
      "image": "https://i.ss.lv/gallery/6/1100/274918/54983509.jpg",
      "description": "",
      "amenities": [],
      "sub_type": null,
      "first_seen": "2026-06-30T10:02:17Z",
      "last_seen": "2026-06-30T10:02:17Z",
      "dedup_hash": "41dc6b94ff86d5ee"
    },
    {
      "id": "ss-lv-hkjnb",
      "source_id": "hkjnb",
      "source_domain": "ss.lv",
      "source_url": "https://www.ss.lv/msg/lv/real-estate/offices/riga/centre/hkjnb.html",
      "type": "commercial",
      "title": "Līdz 17 darba vietām. Plānojums - openspace un kabinetu apvienojums.",
      "district": "Unknown",
      "street": "",
      "price": 2828.0,
      "price_unit": "per_month",
      "currency": "EUR",
      "rooms": 17,
      "area": 3.0,
      "floor": "195",
      "year": null,
      "image": "https://i.ss.lv/gallery/8/1503/375591/75118145.jpg",
      "description": "",
      "amenities": [],
      "sub_type": null,
      "first_seen": "2026-06-30T10:02:17Z",
      "last_seen": "2026-06-30T10:02:17Z",
      "dedup_hash": "1d45fd0f6c8af63e"
    },
    {
      "id": "ss-lv-aboxb",
      "source_id": "aboxb",
      "source_domain": "ss.lv",
      "source_url": "https://www.ss.lv/msg/lv/real-estate/offices/riga/agenskalns/aboxb.html",
      "type": "commercial",
      "title": "Iznomā biroja telpas Pārdaugavā - Kalnciema ielā 87, Rīga, kas atrodas ē",
      "district": "Unknown",
      "street": "",
      "price": 423.0,
      "price_unit": "per_month",
      "currency": "EUR",
      "rooms": 87,
      "area": 87.0,
      "floor": "94",
      "year": null,
      "image": "https://i.ss.lv/gallery/8/1506/376335/75266972.jpg",
      "description": "",
      "amenities": [],
      "sub_type": null,
      "first_seen": "2026-06-30T10:02:17Z",
      "last_seen": "2026-06-30T10:02:17Z",
      "dedup_hash": "ede91925febfe378"
    },
    {
      "id": "ss-lv-djheh",
      "source_id": "djheh",
      "source_domain": "ss.lv",
      "source_url": "https://www.ss.lv/msg/lv/real-estate/offices/riga/centre/djheh.html",
      "type": "commercial",
      "title": "Izīrējam kabinetu Rīgas centrā - Baznīcas 39, 1.st. Kabineta platība:",
      "district": "Unknown",
      "street": "",
      "price": 110.0,
      "price_unit": "per_month",
      "currency": "EUR",
      "rooms": 39,
      "area": 39.0,
      "floor": "10",
      "year": null,
      "image": "https://i.ss.lv/gallery/8/1515/378562/75712387.jpg",
      "description": "",
      "amenities": [],
      "sub_type": null,
      "first_seen": "2026-06-30T10:02:17Z",
      "last_seen": "2026-06-30T10:02:17Z",
      "dedup_hash": "dec91d4567d189fe"
    }
  ]
}